Workbook
Name Annual_Maturity: Assumptions!$B$7
Name Asset_Coupon: Assumptions!$B$5
Name Asset_Par: Assumptions!$B$6
Name CIR_kappa: Assumptions!$B$10
Name CIR_sigma: Assumptions!$B$12
Name CIR_theta: Assumptions!$B$11
Name Expenses: Assumptions!$B$8
Name FABN_Face: Assumptions!$B$2
Name FABN_Maturity: Assumptions!$B$4
Name FABN_Rate: Assumptions!$B$3
Name Initial_Rate: Assumptions!$B$13
Name Months: Assumptions!$B$15
Name Num_Scenarios: Assumptions!$B$14
Name Tax_Rate: Assumptions!$B$9

Sheet Assumptions
A1: C3 RBC Capital Charge — FABN Example: Global Assumptions
A2: FABN Face Value ($) | B2: 100000000
A3: FABN Crediting Rate | B3: 0.035
A4: FABN Maturity (years) | B4: 5
A5: Asset Coupon Rate | B5: 0.04
A6: Asset Total Par ($) | B6: 100000000
A7: Annual Maturing Principal ($) | B7: 20000000
A8: Annual Expenses ($) | B8: 50000
A9: Tax Rate | B9: 0.21
A10: CIR kappa (mean reversion speed) | B10: 0.2
A11: CIR theta (long-run mean rate) | B11: 0.045
A12: CIR sigma (volatility) | B12: 0.06
A13: Initial Rate r0 | B13: 0.04
... A15: Months to Project | B15: 60
A17: All values above flow to CIR Scenarios → Cash Flows → PVAD → All Scenarios Summary → C3 Calculation
A19: TAB GUIDE:
A20: 1. Assumptions | B20: Here
A21: 2. CIR Scenarios | B21: 50 stochastic rate paths (frozen values)
A22: 3. Cash Flows - Scenario 1 | B22: Full annual CF waterfall for Scenario 1
A23: 4. PVAD - Scenario 1 | B23: Discounted deficiency + SGPV for Scenario 1
A24: 5. All Scenarios Summary | B24: SGPV summary for all 50 scenarios
A25: 6. C3 Calculation | B25: CTE weighting → final C3 charge
A26: 7. Sensitivity Analysis | B26: How C3 changes when inputs vary

Sheet CIR Scenarios
A1: 50 Stochastic Interest Rate Scenarios — CIR Model (Monthly, 5-Year Horizon)
A2: Month | B2: Scenario 1 | C2: Scenario 2 | D2: Scenario 3 | E2: Scenario 4 | F2: Scenario 5 | G2: Scenario 6 | H2: Scenario 7 | I2: Scenario 8 | J2: Scenario 9 | K2: Scenario 10 | L2: Scenario 11 | M2: Scenario 12 | N2: Scenario 13 | O2: Scenario 14 | P2: Scenario 15 | Q2: Scenario 16 | R2: Scenario 17 | S2: Scenario 18 | T2: Scenario 19 | U2: Scenario 20 | V2: Scenario 21 | W2: Scenario 22 | X2: Scenario 23 | Y2: Scenario 24 | Z2: Scenario 25 | AA2: Scenario 26 | AB2: Scenario 27 | AC2: Scenario 28 | AD2: Scenario 29 | AE2: Scenario 30 | AF2: Scenario 31 | AG2: Scenario 32 | AH2: Scenario 33 | AI2: Scenario 34 | AJ2: Scenario 35 | AK2: Scenario 36 | AL2: Scenario 37 | AM2: Scenario 38 | AN2: Scenario 39 | AO2: Scenario 40 | AP2: Scenario 41 | AQ2: Scenario 42 | AR2: Scenario 43 | AS2: Scenario 44 | AT2: Scenario 45 | AU2: Scenario 46 | AV2: Scenario 47 | AW2: Scenario 48 | AX2: Scenario 49 | AY2: Scenario 50
A3: 0 | B3: 0.04 | C3: 0.04 | D3: 0.04 | E3: 0.04 | F3: 0.04 | G3: 0.04 | H3: 0.04 | I3: 0.04 | J3: 0.04 | K3: 0.04 | L3: 0.04 | M3: 0.04 | N3: 0.04 | O3: 0.04 | P3: 0.04 | Q3: 0.04 | R3: 0.04 | S3: 0.04 | T3: 0.04 | U3: 0.04 | V3: 0.04 | W3: 0.04 | X3: 0.04 | Y3: 0.04 | Z3: 0.04 | AA3: 0.04 | AB3: 0.04 | AC3: 0.04 | AD3: 0.04 | AE3: 0.04 | AF3: 0.04 | AG3: 0.04 | AH3: 0.04 | AI3: 0.04 | AJ3: 0.04 | AK3: 0.04 | AL3: 0.04 | AM3: 0.04 | AN3: 0.04 | AO3: 0.04 | AP3: 0.04 | AQ3: 0.04 | AR3: 0.04 | AS3: 0.04 | AT3: 0.04 | AU3: 0.04 | AV3: 0.04 | AW3: 0.04 | AX3: 0.04 | AY3: 0.04
A4: 1 | B4: 0.036664229 | C4: 0.040846404 | D4: 0.041422928 | E4: 0.040313323 | F4: 0.044063892 | G4: 0.0439358 | H4: 0.037228924 | I4: 0.04124363 | J4: 0.041911332 | K4: 0.036758132 | L4: 0.039481359 | M4: 0.039275017 | N4: 0.041835595 | O4: 0.0370423 | P4: 0.041464101 | Q4: 0.036266559 | R4: 0.03916805 | S4: 0.040245192 | T4: 0.048026554 | U4: 0.041074229 | V4: 0.041515691 | W4: 0.043669389 | X4: 0.048054818 | Y4: 0.031670775 | Z4: 0.034457318 | AA4: 0.038438075 | AB4: 0.043683536 | AC4: 0.035778297 | AD4: 0.042625403 | AE4: 0.038923252 | AF4: 0.037331531 | AG4: 0.042717065 | AH4: 0.044780121 | AI4: 0.047547582 | AJ4: 0.038425734 | AK4: 0.042511156 | AL4: 0.040268084 | AM4: 0.042778633 | AN4: 0.038542505 | AO4: 0.040157483 | AP4: 0.037840931 | AQ4: 0.047297462 | AR4: 0.039643458 | AS4: 0.041682756 | AT4: 0.037048897 | AU4: 0.036869705 | AV4: 0.041846 | AW4: 0.043625298 | AX4: 0.040877636 | AY4: 0.038315552
A5: 2 | B5: 0.03432227 | C5: 0.03529329 | D5: 0.04244662 | E5: 0.032093421 | F5: 0.045839078 | G5: 0.039312186 | H5: 0.039190128 | I5: 0.047525246 | J5: 0.037815251 | K5: 0.038236351 | L5: 0.040420464 | M5: 0.043177466 | N5: 0.043461206 | O5: 0.038468169 | P5: 0.037204188 | Q5: 0.034196032 | R5: 0.039737806 | S5: 0.040271396 | T5: 0.04701538 | U5: 0.04109789 | V5: 0.044328774 | W5: 0.043344724 | X5: 0.047355046 | Y5: 0.031572015 | Z5: 0.039209093 | AA5: 0.034554699 | AB5: 0.048208157 | AC5: 0.034075814 | AD5: 0.044199495 | AE5: 0.040965993 | AF5: 0.03804676 | AG5: 0.041142209 | AH5: 0.035215928 | AI5: 0.044152672 | AJ5: 0.040576395 | AK5: 0.041902055 | AL5: 0.043818565 | AM5: 0.044184861 | AN5: 0.033407903 | AO5: 0.037532808 | AP5: 0.035133306 | AQ5: 0.044886679 | AR5: 0.035473411 | AS5: 0.041922941 | AT5: 0.033841125 | AU5: 0.040612315 | AV5: 0.042449923 | AW5: 0.039038292 | AX5: 0.04389944 | AY5: 0.043261044
A6: 3 | B6: 0.034482851 | C6: 0.034633435 | D6: 0.045088169 | E6: 0.034011048 | F6: 0.042989624 | G6: 0.039395718 | H6: 0.038379308 | I6: 0.047391682 | J6: 0.041535525 | K6: 0.035670406 | L6: 0.037938141 | M6: 0.044049212 | N6: 0.041116046 | O6: 0.038574359 | P6: 0.039398022 | Q6: 0.033710899 | R6: 0.037847167 | S6: 0.038850128 | T6: 0.047314602 | U6: 0.046965181 | V6: 0.044610643 | W6: 0.036768497 | X6: 0.042569994 | Y6: 0.035167264 | Z6: 0.043310498 | AA6: 0.039705492 | AB6: 0.043988989 | AC6: 0.032023137 | AD6: 0.040345661 | AE6: 0.036119522 | AF6: 0.038689818 | AG6: 0.046687007 | AH6: 0.043031128 | AI6: 0.041095758 | AJ6: 0.040258476 | AK6: 0.04338617 | AL6: 0.046194694 | AM6: 0.04483762 | AN6: 0.02818803 | AO6: 0.032740899 | AP6: 0.03333394 | AQ6: 0.044864573 | AR6: 0.036799685 | AS6: 0.043587264 | AT6: 0.036485891 | AU6: 0.039987701 | AV6: 0.038454148 | AW6: 0.037917941 | AX6: 0.047600722 | AY6: 0.041265371
A7: 4 | B7: 0.032157703 | C7: 0.037516641 | D7: 0.046095798 | E7: 0.031825099 | F7: 0.044718509 | G7: 0.037462012 | H7: 0.03829071 | I7: 0.052866859 | J7: 0.04534825 | K7: 0.036906839 | L7: 0.039320652 | M7: 0.042831628 | N7: 0.046081592 | O7: 0.034255551 | P7: 0.040290349 | Q7: 0.036773547 | R7: 0.035814477 | S7: 0.044043696 | T7: 0.040178412 | U7: 0.046010435 | V7: 0.044385439 | W7: 0.038486156 | X7: 0.042195515 | Y7: 0.029103633 | Z7: 0.044342454 | AA7: 0.039766427 | AB7: 0.042835076 | AC7: 0.033524087 | AD7: 0.036902618 | AE7: 0.038361507 | AF7: 0.033135834 | AG7: 0.042591354 | AH7: 0.044224442 | AI7: 0.035991303 | AJ7: 0.041243646 | AK7: 0.042271849 | AL7: 0.053682827 | AM7: 0.037205818 | AN7: 0.027062584 | AO7: 0.033394419 | AP7: 0.032994863 | AQ7: 0.052866501 | AR7: 0.044003436 | AS7: 0.04615681 | AT7: 0.037733613 | AU7: 0.032418341 | AV7: 0.040640112 | AW7: 0.032483431 | AX7: 0.045039453 | AY7: 0.038548029
A8: 5 | B8: 0.026269906 | C8: 0.035895069 | D8: 0.052716666 | E8: 0.037775112 | F8: 0.048247918 | G8: 0.034077553 | H8: 0.03916101 | I8: 0.053713251 | J8: 0.044221287 | K8: 0.035575811 | L8: 0.037645199 | M8: 0.039502509 | N8: 0.046413 | O8: 0.033849851 | P8: 0.048296952 | Q8: 0.03632629 | R8: 0.036543901 | S8: 0.040949212 | T8: 0.041142964 | U8: 0.043784985 | V8: 0.047599612 | W8: 0.039195716 | X8: 0.041918129 | Y8: 0.023938396 | Z8: 0.038338652 | AA8: 0.043204453 | AB8: 0.044030629 | AC8: 0.04918466 | AD8: 0.033459101 | AE8: 0.037742133 | AF8: 0.033596863 | AG8: 0.037831627 | AH8: 0.045542501 | AI8: 0.035712283 | AJ8: 0.043106821 | AK8: 0.047594224 | AL8: 0.055981622 | AM8: 0.038944077 | AN8: 0.026924858 | AO8: 0.034012041 | AP8: 0.03786962 | AQ8: 0.048031077 | AR8: 0.03764566 | AS8: 0.041403401 | AT8: 0.040341121 | AU8: 0.033626426 | AV8: 0.041562471 | AW8: 0.030628586 | AX8: 0.043657215 | AY8: 0.037787549
A9: 6 | B9: 0.032562603 | C9: 0.034431208 | D9: 0.048982491 | E9: 0.042491424 | F9: 0.043928058 | G9: 0.036530728 | H9: 0.039936858 | I9: 0.058070693 | J9: 0.038460912 | K9: 0.04432472 | L9: 0.038997688 | M9: 0.038483331 | N9: 0.047816448 | O9: 0.031965891 | P9: 0.044952011 | Q9: 0.035916592 | R9: 0.041360579 | S9: 0.047097438 | T9: 0.032731553 | U9: 0.042019069 | V9: 0.048566961 | W9: 0.037969551 | X9: 0.045390482 | Y9: 0.025508587 | Z9: 0.034776812 | AA9: 0.048516863 | AB9: 0.038749617 | AC9: 0.048481422 | AD9: 0.033027635 | AE9: 0.035025726 | AF9: 0.030467465 | AG9: 0.029934424 | AH9: 0.048213065 | AI9: 0.033136235 | AJ9: 0.040992732 | AK9: 0.05003265 | AL9: 0.054626162 | AM9: 0.037802751 | AN9: 0.023926205 | AO9: 0.038252636 | AP9: 0.039615352 | AQ9: 0.051181037 | AR9: 0.036854322 | AS9: 0.043374641 | AT9: 0.034211323 | AU9: 0.032183252 | AV9: 0.042885493 | AW9: 0.033163226 | AX9: 0.044757791 | AY9: 0.032160663
A10: 7 | B10: 0.035455093 | C10: 0.030378004 | D10: 0.046366178 | E10: 0.041205854 | F10: 0.04380608 | G10: 0.035565216 | H10: 0.040184453 | I10: 0.052430997 | J10: 0.039115312 | K10: 0.047453283 | L10: 0.035535425 | M10: 0.034966981 | N10: 0.044426527 | O10: 0.028292563 | P10: 0.048737622 | Q10: 0.036018989 | R10: 0.041360815 | S10: 0.044512169 | T10: 0.03255636 | U10: 0.040935569 | V10: 0.040871311 | W10: 0.037827204 | X10: 0.041112987 | Y10: 0.029258352 | Z10: 0.039176661 | AA10: 0.050996512 | AB10: 0.039459441 | AC10: 0.041121735 | AD10: 0.031694766 | AE10: 0.036971194 | AF10: 0.032837257 | AG10: 0.028013042 | AH10: 0.042800987 | AI10: 0.036152926 | AJ10: 0.040575675 | AK10: 0.050565695 | AL10: 0.058573571 | AM10: 0.035391686 | AN10: 0.022385296 | AO10: 0.03245239 | AP10: 0.036469567 | AQ10: 0.045975856 | AR10: 0.040862612 | AS10: 0.04354711 | AT10: 0.034565115 | AU10: 0.029571457 | AV10: 0.045313063 | AW10: 0.033024718 | AX10: 0.043265291 | AY10: 0.033514783
A11: 8 | B11: 0.036153921 | C11: 0.029033603 | D11: 0.045678574 | E11: 0.041569419 | F11: 0.040005524 | G11: 0.034305816 | H11: 0.040386198 | I11: 0.048931302 | J11: 0.03192043 | K11: 0.045786314 | L11: 0.034733653 | M11: 0.038050743 | N11: 0.0423288 | O11: 0.031838765 | P11: 0.04998945 | Q11: 0.035204084 | R11: 0.043218683 | S11: 0.037477167 | T11: 0.033360814 | U11: 0.039929893 | V11: 0.041718394 | W11: 0.040434122 | X11: 0.038899012 | Y11: 0.029906504 | Z11: 0.050453202 | AA11: 0.047575968 | AB11: 0.038357609 | AC11: 0.043828792 | AD11: 0.029649633 | AE11: 0.039362825 | AF11: 0.037191191 | AG11: 0.026253639 | AH11: 0.052285783 | AI11: 0.032797379 | AJ11: 0.045048863 | AK11: 0.044661544 | AL11: 0.052437255 | AM11: 0.038236008 | AN11: 0.020958916 | AO11: 0.025546321 | AP11: 0.038134646 | AQ11: 0.050820967 | AR11: 0.042927649 | AS11: 0.043018613 | AT11: 0.034884653 | AU11: 0.031263818 | AV11: 0.05009939 | AW11: 0.0372869 | AX11: 0.044423111 | AY11: 0.037989807
A12: 9 | B12: 0.035422735 | C12: 0.025634682 | D12: 0.046626151 | E12: 0.040844585 | F12: 0.041237196 | G12: 0.038021524 | H12: 0.036952826 | I12: 0.048080616 | J12: 0.033853143 | K12: 0.044900441 | L12: 0.036301727 | M12: 0.034825246 | N12: 0.048658811 | O12: 0.030634475 | P12: 0.050757504 | Q12: 0.035368597 | R12: 0.043592483 | S12: 0.035909426 | T12: 0.030915281 | U12: 0.039050275 | V12: 0.041731336 | W12: 0.042049879 | X12: 0.046046573 | Y12: 0.030787369 | Z12: 0.056631697 | AA12: 0.046304216 | AB12: 0.037194977 | AC12: 0.0453583 | AD12: 0.034204834 | AE12: 0.033154378 | AF12: 0.042087246 | AG12: 0.033852108 | AH12: 0.05201204 | AI12: 0.036821636 | AJ12: 0.045853815 | AK12: 0.044189281 | AL12: 0.052550485 | AM12: 0.037956149 | AN12: 0.019253939 | AO12: 0.024304371 | AP12: 0.040898641 | AQ12: 0.050609369 | AR12: 0.042633287 | AS12: 0.039858896 | AT12: 0.039430513 | AU12: 0.024999142 | AV12: 0.046046291 | AW12: 0.038524928 | AX12: 0.041466484 | AY12: 0.037642034
A13: 10 | B13: 0.034189958 | C13: 0.028201932 | D13: 0.047764171 | E13: 0.046533012 | F13: 0.041636059 | G13: 0.039567534 | H13: 0.041354394 | I13: 0.045732039 | J13: 0.032206835 | K13: 0.051238984 | L13: 0.033814709 | M13: 0.038594914 | N13: 0.038974811 | O13: 0.03296618 | P13: 0.05734338 | Q13: 0.037836489 | R13: 0.042260963 | S13: 0.037775352 | T13: 0.035087318 | U13: 0.030899966 | V13: 0.043681727 | W13: 0.036005885 | X13: 0.046144464 | Y13: 0.03267975 | Z13: 0.055972275 | AA13: 0.049210533 | AB13: 0.040734722 | AC13: 0.043042193 | AD13: 0.041738683 | AE13: 0.035156856 | AF13: 0.046826375 | AG13: 0.031460583 | AH13: 0.050190831 | AI13: 0.037060163 | AJ13: 0.038780614 | AK13: 0.040621382 | AL13: 0.061423701 | AM13: 0.041232293 | AN13: 0.019809632 | AO13: 0.023820549 | AP13: 0.040711983 | AQ13: 0.05174414 | AR13: 0.04853456 | AS13: 0.041636564 | AT13: 0.034763934 | AU13: 0.02473329 | AV13: 0.049343033 | AW13: 0.038426381 | AX13: 0.049844099 | AY13: 0.033921935
A14: 11 | B14: 0.032146135 | C14: 0.026242812 | D14: 0.05020322 | E14: 0.052103385 | F14: 0.040755509 | G14: 0.035166974 | H14: 0.038025671 | I14: 0.045315577 | J14: 0.030015744 | K14: 0.061860036 | L14: 0.028970374 | M14: 0.035973972 | N14: 0.044813695 | O14: 0.034234795 | P14: 0.056689982 | Q14: 0.0399941 | R14: 0.042722351 | S14: 0.040311575 | T14: 0.032928545 | U14: 0.031727472 | V14: 0.044449557 | W14: 0.037169194 | X14: 0.046785375 | Y14: 0.028488969 | Z14: 0.049306121 | AA14: 0.048750352 | AB14: 0.038305763 | AC14: 0.046527499 | AD14: 0.038644461 | AE14: 0.037058707 | AF14: 0.035741728 | AG14: 0.032279091 | AH14: 0.051845879 | AI14: 0.036761224 | AJ14: 0.037859311 | AK14: 0.038464509 | AL14: 0.067817538 | AM14: 0.044276565 | AN14: 0.020190313 | AO14: 0.025441019 | AP14: 0.042887964 | AQ14: 0.058315094 | AR14: 0.043850702 | AS14: 0.04013781 | AT14: 0.031768233 | AU14: 0.022517021 | AV14: 0.050745846 | AW14: 0.035176925 | AX14: 0.048736164 | AY14: 0.037483201
... A26: 23 | B26: 0.028250741 | C26: 0.016394348 | D26: 0.032192232 | E26: 0.049470182 | F26: 0.043329004 | G26: 0.028078448 | H26: 0.028755651 | I26: 0.042711018 | J26: 0.028700229 | K26: 0.052069946 | L26: 0.032650994 | M26: 0.044838995 | N26: 0.026616975 | O26: 0.039163636 | P26: 0.059687584 | Q26: 0.027215788 | R26: 0.031709252 | S26: 0.029757754 | T26: 0.030944343 | U26: 0.048519487 | V26: 0.042119966 | W26: 0.049209632 | X26: 0.034859653 | Y26: 0.025570565 | Z26: 0.051411943 | AA26: 0.048103274 | AB26: 0.041565431 | AC26: 0.042958039 | AD26: 0.038863377 | AE26: 0.033131931 | AF26: 0.02199957 | AG26: 0.053057366 | AH26: 0.083457661 | AI26: 0.030179208 | AJ26: 0.043812315 | AK26: 0.029331741 | AL26: 0.092276324 | AM26: 0.041676503 | AN26: 0.027177785 | AO26: 0.033305538 | AP26: 0.050022168 | AQ26: 0.054819996 | AR26: 0.049062918 | AS26: 0.041898814 | AT26: 0.042675142 | AU26: 0.018787241 | AV26: 0.03625379 | AW26: 0.026063571 | AX26: 0.067361973 | AY26: 0.043555528
A27: 24 | B27: 0.026814282 | C27: 0.015718713 | D27: 0.025313092 | E27: 0.049980893 | F27: 0.049967831 | G27: 0.031606985 | H27: 0.026482387 | I27: 0.038386054 | J27: 0.028877416 | K27: 0.047026519 | L27: 0.031711892 | M27: 0.049686857 | N27: 0.029291822 | O27: 0.040855242 | P27: 0.058669136 | Q27: 0.020262241 | R27: 0.031143513 | S27: 0.029153765 | T27: 0.026912774 | U27: 0.045592123 | V27: 0.042876877 | W27: 0.048476371 | X27: 0.029583296 | Y27: 0.022143605 | Z27: 0.05210127 | AA27: 0.051883639 | AB27: 0.042139781 | AC27: 0.047142767 | AD27: 0.038178993 | AE27: 0.03337399 | AF27: 0.020248874 | AG27: 0.051142474 | AH27: 0.082592557 | AI27: 0.030311995 | AJ27: 0.044856071 | AK27: 0.030944791 | AL27: 0.097128531 | AM27: 0.043403407 | AN27: 0.02503919 | AO27: 0.02776586 | AP27: ho | AQ27: 0.054860059 | AR27: 0.047320293 | AS27: 0.035454948 | AT27: 0.038205123 | AU27: 0.016639148 | AV27: 0.03451446 | AW27: 0.026385147 | AX27: 0.069698467 | AY27: 0.045504756
A28: 25 | B28: 0.028818467 | C28: 0.019114285 | D28: 0.021727941 | E28: 0.052393806 | F28: 0.047399884 | G28: 0.034050135 | H28: 0.028400116 | I28: 0.040413029 | J28: 0.03514252 | K28: 0.042610742 | L28: 0.031085202 | M28: 0.047736052 | N28: 0.032093517 | O28: 0.044786042 | P28: 0.0571032 | Q28: 0.024805189 | R28: 0.031420621 | S28: 0.022807221 | T28: 0.028901708 | U28: 0.048244296 | V28: 0.040180938 | W28: 0.042094784 | X28: 0.032895115 | Y28: 0.022637307 | Z28: 0.048263083 | AA28: 0.049664743 | AB28: 0.04049671 | AC28: 0.049142385 | AD28: 0.042388886 | AE28: 0.035090416 | AF28: 0.021861625 | AG28: 0.051192409 | AH28: 0.091235001 | AI28: 0.026940024 | AJ28: 0.043762836 | AK28: 0.027964659 | AL28: 0.091753659 | AM28: 0.051533024 | AN28: 0.024362627 | AO28: 0.024016706 | AP28: 0.051015735 | AQ28: 0.053636742 | AR28: 0.038172959 | AS28: 0.028382094 | AT28: 0.038522041 | AU28: 0.017064095 | AV28: 0.032717224 | AW28: 0.0323143 | AX28: 0.067982655 | AY28: 0.043294191
A29: 26 | B29: 0.02908693 | C29: 0.014914978 | D29: 0.02247858 | E29: 0.051029884 | F29: 0.045790095 | G29: 0.034425821 | H29: 0.032298795 | I29: 0.039284449 | J29: 0.036149627 | K29: 0.048195471 | L29: 0.031690321 | M29: 0.051933751 | N29: 0.034521067 | O29: 0.044312472 | P29: 0.057515509 | Q29: 0.023509229 | R29: 0.031786133 | S29: 0.024908828 | T29: 0.032670634 | U29: 0.044522545 | V29: 0.035195308 | W29: 0.044296778 | X29: 0.036029524 | Y29: 0.021639944 | Z29: 0.045112613 | AA29: 0.054402963 | AB29: 0.039116741 | AC29: 0.045156294 | AD29: 0.040175299 | AE29: 0.031113002 | AF29: 0.022062694 | AG29: 0.05197306 | AH29: 0.093691417 | AI29: 0.026971953 | AJ29: 0.047540261 | AK29: 0.025280189 | AL29: 0.097809104 | AM29: 0.050053194 | AN29: 0.024513904 | AO29: 0.025950151 | AP29: 0.047510552 | AQ29: 0.053396991 | AR29: 0.040531923 | AS29: 0.029980955 | AT29: 0.039810798 | AU29: 0.017241456 | AV29: 0.032847951 | AW29: 0.035976262 | AX29: 0.074234869 | AY29: 0.043113611
A30: 27 | B30: 0.031187491 | C30: 0.01536318 | D30: 0.026405727 | E30: 0.0506119 | F30: 0.044893018 | G30: 0.035339272 | H30: 0.024846159 | I30: 0.039572513 | J30: 0.041124781 | K30: 0.045388277 | L30: 0.028407071 | M30: 0.052498961 | N30: 0.037928115 | O30: 0.04560833 | P30: 0.055440382 | Q30: 0.027591738 | R30: 0.026636754 | S30: 0.026747015 | T30: 0.036704037 | U30: 0.045928505 | V30: 0.031716691 | W30: 0.042700842 | X30: 0.036786118 | Y30: 0.020081763 | Z30: 0.04270533 | AA30: 0.050358245 | AB30: 0.039584353 | AC30: 0.049571787 | AD30: 0.039740911 | AE30: 0.027137028 | AF30: 0.019612123 | AG30: 0.050107326 | AH30: 0.088317632 | AI30: 0.028009874 | AJ30: 0.052257861 | AK30: 0.020686256 | AL30: 0.092565557 | AM30: 0.050317616 | AN30: 0.027468914 | AO30: 0.026708932 | AP30: 0.046770168 | AQ30: 0.056751298 | AR30: 0.040501246 | AS30: 0.027734374 | AT30: 0.041736502 | AU30: 0.017298205 | AV30: 0.024609435 | AW30: 0.035320451 | AX30: 0.072631557 | AY30: 0.041628217
A31: 28 | B31: 0.031390263 | C31: 0.01609809 | D31: 0.028827132 | E31: 0.048656109 | F31: 0.045682439 | G31: 0.035260443 | H31: 0.023452083 | I31: 0.044050846 | J31: 0.038770306 | K31: 0.044290432 | L31: 0.025806503 | M31: 0.052584931 | N31: 0.039637121 | O31: 0.05282311 | P31: 0.06398486 | Q31: 0.030336038 | R31: 0.02843046 | S31: 0.02392986 | T31: 0.036407962 | U31: 0.037638195 | V31: 0.034934018 | W31: 0.042057133 | X31: 0.033089854 | Y31: 0.023018588 | Z31: 0.035484154 | AA31: 0.054082015 | AB31: 0.038743733 | AC31: 0.049206063 | AD31: 0.042049653 | AE31: 0.026166112 | AF31: 0.020338655 | AG31: 0.046728819 | AH31: 0.090671323 | AI31: 0.027920458 | AJ31: 0.055542117 | AK31: 0.018370425 | AL31: 0.083170468 | AM31: 0.046502811 | AN31: 0.028105638 | AO31: 0.025361889 | AP31: 0.047163847 | AQ31: 0.0556959 | AR31: 0.046233056 | AS31: 0.026164694 | AT31: 0.039917982 | AU31: 0.020294954 | AV31: 0.022795717 | AW31: 0.034912599 | AX31: 0.072561989 | AY31: 0.049886904
A32: 29 | B32: 0.03426035 | C32: 0.019429712 | D32: 0.029075015 | E32: 0.049616906 | F32: 0.038647064 | G32: 0.035933465 | H32: 0.023022546 | I32: 0.037841324 | J32: 0.039031022 | K32: 0.046510034 | L32: 0.023838342 | M32: 0.04867872 | N32: 0.038279948 | O32: 0.054821128 | P32: 0.064368097 | Q32: 0.029272932 | R32: 0.029094082 | S32: 0.02224176 | T32: 0.034805195 | U32: 0.028725375 | V32: 0.034577815 | W32: 0.045176613 | X32: 0.037615691 | Y32: 0.023669172 | Z32: 0.031386933 | AA32: 0.052900258 | AB32: 0.039484472 | AC32: 0.049733913 | AD32: 0.042237597 | AE32: 0.023991597 | AF32: 0.017899353 | AG32: 0.049532052 | AH32: 0.085444007 | AI32: 0.032414948 | AJ32: 0.048569966 | AK32: 0.018876096 | AL32: 0.0881197 | AM32: 0.051394619 | AN32: 0.025178314 | AO32: 0.02428847 | AP32: 0.048088929 | AQ32: 0.057229507 | AR32: 0.0434828 | AS32: 0.023218427 | AT32: 0.040485848 | AU32: 0.020478494 | AV32: 0.025278932 | AW32: 0.040029671 | AX32: 0.063318747 | AY32: 0.05012352
A33: 30 | B33: 0.028942228 | C33: 0.021065545 | D33: 0.028611587 | E33: 0.048596527 | F33: 0.035090572 | G33: 0.035120177 | H33: 0.026756066 | I33: 0.037272555 | J33: 0.034406195 | K33: 0.049191513 | L33: 0.02223372 | M33: 0.045378089 | N33: 0.032547671 | O33: 0.054026744 | P33: 0.069143526 | Q33: 0.025885813 | R33: 0.02958208 | S33: 0.027120397 | T33: 0.034040802 | U33: 0.027256578 | V33: 0.034054845 | W33: 0.040935751 | X33: 0.036816632 | Y33: 0.023310748 | Z33: 0.033787796 | AA33: 0.057634723 | AB33: 0.047404007 | AC33: 0.045393318 | AD33: 0.04412428 | AE33: 0.027068778 | AF33: 0.015314267 | AG33: 0.049074175 | AH33: 0.086856368 | AI33: 0.033650813 | AJ33: 0.046187076 | AK33: 0.020156612 | AL33: 0.090882127 | AM33: 0.052621282 | AN33: 0.023841826 | AO33: 0.028181026 | AP33: 0.052636932 | AQ33: 0.052988748 | AR33: 0.042981524 | AS33: 0.019083281 | AT33: 0.043138712 | AU33: 0.021358301 | AV33: 0.022754138 | AW33: 0.039891241 | AX33: 0.058938424 | AY33: 0.048337965
A34: 31 | B34: 0.033960965 | C34: 0.018423633 | D34: 0.029566191 | E34: 0.04882423 | F34: 0.034581986 | G34: 0.034864565 | H34: 0.022501197 | I34: 0.038060906 | J34: 0.035669948 | K34: 0.055360982 | L34: 0.020353182 | M34: 0.044175694 | N34: 0.034613905 | O34: 0.063176463 | P34: 0.070092579 | Q34: 0.025780392 | R34: 0.027759904 | S34: 0.024388729 | T34: 0.036630755 | U34: 0.029284409 | V34: 0.034842967 | W34: 0.042773395 | X34: 0.039539396 | Y34: 0.022585533 | Z34: 0.031805332 | AA34: 0.057452816 | AB34: 0.043737364 | AC34: 0.046461436 | AD34: 0.041733612 | AE34: 0.031766177 | AF34: 0.019353868 | AG34: 0.047276054 | AH34: 0.083353694 | AI34: 0.036501058 | AJ34: 0.044237896 | AK34: 0.019555918 | AL34: 0.085420348 | AM34: 0.05156824 | AN34: 0.027282808 | AO34: 0.027927047 | AP34: 0.049306838 | AQ34: 0.04924765 | AR34: 0.042611891 | AS34: 0.017097971 | AT34: 0.045023045 | AU34: 0.017821389 | AV34: 0.022780846 | AW34: 0.046289954 | AX34: 0.06416442 | AY34: 0.052110258
A35: 32 | B35: 0.03494559 | C35: 0.022163649 | D35: 0.030913966 | E35: 0.04869755 | F35: 0.035559474 | G35: 0.03714586 | H35: 0.02162271 | I35: 0.036576587 | J35: 0.0377328 | K35: 0.058234077 | L35: 0.022945945 | M35: 0.038576224 | N35: 0.038638303 | O35: 0.053265713 | P35: 0.066291831 | Q35: 0.017443667 | R35: 0.029642909 | S35: 0.025630022 | T35: 0.039195023 | U35: 0.029241507 | V35: 0.029425771 | W35: 0.040573147 | X35: 0.039768385 | Y35: 0.019612961 | Z35: 0.032960941 | AA35: 0.054903318 | AB35: 0.044752013 | AC35: 0.042886707 | AD35: 0.040244958 | AE35: 0.035945669 | AF35: 0.018429767 | AG35: 0.046510524 | AH35: 0.080875447 | AI35: 0.036756376 | AJ35: 0.043558574 | AK35: 0.018575413 | AL35: 0.082504291 | AM35: 0.053708613 | AN35: 0.033374494 | AO35: 0.031706412 | AP35: 0.047012042 | AQ35: 0.054060991 | AR35: 0.043313181 | AS35: 0.016891712 | AT35: 0.048256631 | AU35: 0.020042058 | AV35: 0.027085974 | AW35: 0.050113167 | AX35: 0.066880376 | AY35: 0.048026812
A36: 33 | B36: 0.035054441 | C36: 0.020996109 | D36: 0.029127349 | E36: 0.048624716 | F36: 0.03683899 | G36: 0.035271242 | H36: 0.021562246 | I36: 0.039641902 | J36: 0.042220243 | K36: 0.053450835 | L36: 0.022958005 | M36: 0.037281435 | N36: 0.035381977 | O36: 0.050695599 | P36: 0.063500731 | Q36: 0.018648945 | R36: 0.029480751 | S36: 0.026577963 | T36: 0.035464968 | U36: 0.030607744 | V36: 0.026841274 | W36: 0.041044701 | X36: 0.042858905 | Y36: 0.020143802 | Z36: 0.031461283 | AA36: 0.054653941 | AB36: 0.049974779 | AC36: 0.037840056 | AD36: 0.041901107 | AE36: 0.037265281 | AF36: 0.020468774 | AG36: 0.051637461 | AH36: 0.079559008 | AI36: 0.038286492 | AJ36: 0.046736119 | AK36: 0.019249092 | AL36: 0.083017378 | AM36: 0.051146581 | AN36: 0.035412063 | AO36: 0.030378079 | AP36: 0.0508219 | AQ36: 0.048585469 | AR36: 0.046762795 | AS36: 0.020516959 | AT36: 0.048820004 | AU36: 0.020166632 | AV36: 0.029246982 | AW36: 0.05440661 | AX36: 0.060739445 | AY36: 0.043616027
A37: 34 | B37: 0.033359564 | C37: 0.020084576 | D37: 0.024293225 | E37: 0.052308901 | F37: 0.031654347 | G37: 0.027664829 | H37: 0.014790159 | I37: 0.035945607 | J37: 0.038510168 | K37: 0.053241678 | L37: 0.017086009 | M37: 0.037066016 | N37: 0.034181141 | O37: 0.048152584 | P37: 0.06622816 | Q37: 0.020202056 | R37: 0.031747567 | S37: 0.029219298 | T37: 0.03381439 | U37: 0.0286228 | V37: 0.027419801 | W37: 0.0420126 | X37: 0.050777458 | Y37: 0.018048052 | Z37: 0.033441926 | AA37: 0.059734472 | AB37: 0.055861715 | AC37: 0.038782732 | AD37: 0.037283998 | AE37: 0.035130869 | AF37: 0.020268969 | AG37: 0.049896118 | AH37: 0.077768614 | AI37: 0.034799671 | AJ37: 0.043995916 | AK37: 0.022046168 | AL37: 0.080908733 | AM37: 0.054453311 | AN37: 0.033938786 | AO37: 0.036806297 | AP37: 0.05516277 | AQ37: 0.048186802 | AR37: 0.043438316 | AS37: 0.020167322 | AT37: 0.046201714 | AU37: 0.016023149 | AV37: 0.032516979 | AW37: 0.055897158 | AX37: 0.062520684 | AY37: 0.04554963
A38: 35 | B38: 0.036997818 | C38: 0.018292029 | D38: 0.020134797 | E38: 0.055382687 | F38: 0.031147383 | G38: 0.023858641 | H38: 0.016516567 | I38: 0.034502448 | J38: 0.041617638 | K38: 0.056553666 | L38: 0.014907706 | M38: 0.036549801 | N38: 0.037129201 | O38: 0.044727527 | P38: 0.06776915 | Q38: 0.016597679 | R38: 0.036158262 | S38: 0.028989094 | T38: 0.036822783 | U38: 0.035308176 | V38: 0.024778092 | W38: 0.045241762 | X38: 0.050184158 | Y38: 0.01658125 | Z38: 0.036940773 | AA38: 0.059909294 | AB38: 0.050947428 | AC38: 0.046822916 | AD38: 0.03846359 | AE38: 0.041605905 | AF38: 0.022787078 | AG38: 0.055357466 | AH38: 0.08197612 | AI38: 0.035916035 | AJ38: 0.045591669 | AK38: 0.021469824 | AL38: 0.081027923 | AM38: 0.050183169 | AN38: 0.035293267 | AO38: 0.035334686 | AP38: 0.057002877 | AQ38: 0.038492954 | AR38: 0.045287278 | AS38: 0.020675966 | AT38: 0.047452634 | AU38: 0.01612499 | AV38: 0.028608583 | AW38: 0.05714481 | AX38: 0.057136004 | AY38: 0.042695679
A39: 36 | B39: 0.034798014 | C39: 0.016419829 | D39: 0.025392506 | E39: 0.059689927 | F39: 0.027336218 | G39: 0.023292085 | H39: 0.01765339 | I39: 0.034867309 | J39: 0.042926693 | K39: 0.056462283 | L39: 0.011988254 | M39: 0.034742225 | N39: 0.040434057 | O39: 0.044509237 | P39: 0.066539839 | Q39: 0.019565084 | R39: 0.037798511 | S39: 0.027391651 | T39: 0.041392232 | U39: 0.044635627 | V39: 0.025712833 | W39: 0.040446311 | X39: 0.045244282 | Y39: 0.017304522 | Z39: 0.043843982 | AA39: 0.063263342 | AB39: 0.053983005 | AC39: 0.047024446 | AD39: 0.039781314 | AE39: 0.036353381 | AF39: 0.027050904 | AG39: 0.060953873 | AH39: 0.082061973 | AI39: 0.037276103 | AJ39: 0.039886685 | AK39: 0.020889802 | AL39: 0.093001949 | AM39: 0.053030563 | AN39: 0.031808729 | AO39: 0.036691852 | AP39: 0.063491772 | AQ39: 0.041716316 | AR39: 0.050389879 | AS39: 0.017475987 | AT39: 0.045577822 | AU39: 0.017466791 | AV39: 0.026316012 | AW39: 0.056013503 | AX39: 0.062709458 | AY39: 0.040049516
... A63: 60 | B63: 0.026636707 | C63: 0.029543433 | D63: 0.043237277 | E63: 0.061564181 | F63: 0.042354835 | G63: 0.017418345 | H63: 0.027768878 | I63: 0.029321608 | J63: 0.042930592 | K63: 0.049759314 | L63: 0.023360262 | M63: 0.020852597 | N63: 0.04865518 | O63: 0.073042157 | P63: 0.074937691 | Q63: 0.059935523 | R63: 0.059590702 | S63: 0.026416286 | T63: 0.040173013 | U63: 0.054666266 | V63: 0.025240343 | W63: 0.054369404 | X63: 0.047757717 | Y63: 0.020637744 | Z63: 0.026662595 | AA63: 0.062304066 | AB63: 0.053600921 | AC63: 0.10235828 | AD63: 0.032180532 | AE63: 0.045787094 | AF63: 0.033678128 | AG63: 0.045724931 | AH63: 0.072333598 | AI63: 0.090432994 | AJ63: 0.044791715 | AK63: 0.020026673 | AL63: 0.07752375 | AM63: 0.040228031 | AN63: 0.050536867 | AO63: 0.047203923 | AP63: 0.041553712 | AQ63: 0.019745145 | AR63: 0.075533951 | AS63: 0.026921909 | AT63: 0.031177092 | AU63: 0.033680205 | AV63: 0.0075195557 | AW63: 0.063632754 | AX63: 0.059063061 | AY63: 0.031343659

Sheet Cash Flows - Scenario 1
A1: Cash Flow Projection — Scenario 1 (Detailed Teaching Sheet)
A2: Every component is shown explicitly. Inflows (green) – Outflows (red) = Net Cash (blue). Accumulated Cash tracks the running balance.
A3: Year | B3: Outstanding Asset Par ($) | C3: Bond Coupons ($) | D3: Maturing Principal ($) | E3: Annual Rate (Scen 1) | F3: Reinvestment Income ($) | G3: Total Cash In ($) | H3: FABN Interest ($) | I3: FABN Principal ($) | J3: Expenses ($) | K3: Total Cash Out ($) | L3: Net Cash ($) | M3: Accumulated Cash ($)
A4: 1 | B4: =Asset_Par-(A4-1)*Annual_Maturity -> 100000000 | C4: =B4*Asset_Coupon -> 4000000 | D4: =Annual_Maturity -> 20000000 | E4: =AVERAGE('CIR Scenarios'!B4:B15) -> 0.034090682 | F4: 0 | G4: =C4+D4+F4 -> 24000000 | H4: =FABN_Face*FABN_Rate -> 3500000 | I4: =IF(A4=FABN_Maturity,FABN_Face,0) -> 0 | J4: =Expenses -> 50000 | K4: =H4+I4+J4 -> 3550000 | L4: =G4-K4 -> 20450000 | M4: =L4 -> 20450000
A5: 2 | B5: =Asset_Par-(A5-1)*Annual_Maturity -> 80000000 | C5: =B5*Asset_Coupon -> 3200000 | D5: =Annual_Maturity -> 20000000 | E5: =AVERAGE('CIR Scenarios'!B16:B27) -> 0.033256437 | F5: =IF(M4>0,M4*E5,0) -> 680094.14 | G5: =C5+D5+F5 -> 23880094 | H5: =FABN_Face*FABN_Rate -> 3500000 | I5: =IF(A5=FABN_Maturity,FABN_Face,0) -> 0 | J5: =Expenses -> 50000 | K5: =H5+I5+J5 -> 3550000 | L5: =G5-K5 -> 20330094 | M5: =M4+L5 -> 40780094
A6: 3 | B6: =Asset_Par-(A6-1)*Annual_Maturity -> 60000000 | C6: =B6*Asset_Coupon -> 2400000 | D6: =Annual_Maturity -> 20000000 | E6: =AVERAGE('CIR Scenarios'!B28:B39) -> 0.03273351 | F6: =IF(M5>0,M5*E6,0) -> 1334875.6 | G6: =C6+D6+F6 -> 23734876 | H6: =FABN_Face*FABN_Rate -> 3500000 | I6: =IF(A6=FABN_Maturity,FABN_Face,0) -> 0 | J6: =Expenses -> 50000 | K6: =H6+I6+J6 -> 3550000 | L6: =G6-K6 -> 20184876 | M6: =M5+L6 -> 60964970
A7: 4 | B7: =Asset_Par-(A7-1)*Annual_Maturity -> 40000000 | C7: =B7*Asset_Coupon -> 1600000 | D7: =Annual_Maturity -> 20000000 | E7: =AVERAGE('CIR Scenarios'!B40:B51) -> 0.036005773 | F7: =IF(M6>0,M6*E7,0) -> 2195090.8 | G7: =C7+D7+F7 -> 23795091 | H7: =FABN_Face*FABN_Rate -> 3500000 | I7: =IF(A7=FABN_Maturity,FABN_Face,0) -> 0 | J7: =Expenses -> 50000 | K7: =H7+I7+J7 -> 3550000 | L7: =G7-K7 -> 20245091 | M7: =M6+L7 -> 81210061
A8: 5 | B8: =Asset_Par-(A8-1)*Annual_Maturity -> 20000000 | C8: =B8*Asset_Coupon -> 800000 | D8: =Annual_Maturity -> 20000000 | E8: =AVERAGE('CIR Scenarios'!B52:B63) -> 0.033865587 | F8: =IF(M7>0,M7*E8,0) -> 2750226.4 | G8: =C8+D8+F8 -> 23550226 | H8: =FABN_Face*FABN_Rate -> 3500000 | I8: =IF(A8=FABN_Maturity,FABN_Face,0) -> 100000000 | J8: =Expenses -> 50000 | K8: =H8+I8+J8 -> 103550000 | L8: =G8-K8 -> -79999774 | M8: =M7+L8 -> 1210287
A10: → These accumulated cash values feed into 'PVAD - Scenario 1' for discounting and SGPV calculation

Sheet PVAD - Scenario 1
A1: Present Value of Accumulated Deficiencies (PVAD) — Scenario 1
A2: PVAD = MAX(0, -AccumCash) × Cumulative Discount Factor. SGPV = Maximum PVAD across all years. Used to size the C3 capital charge.
A3: Year | B3: Accumulated Cash ($) | C3: Deficiency ($) | D3: Cumul. Discount Factor | E3: PVAD ($) | G3: [Helper] Month | H3: Monthly Rate (Scen 1) | I3: Running Cum. DF
A4: 1 | B4: ='Cash Flows - Scenario 1'!M4 -> 20450000 | C4: =MAX(0,-B4) -> 0 | D4: =I15 -> 0.96653095 | E4: =C4*D4 -> 0 | G4: 1 | H4: ='CIR Scenarios'!B4 -> 0.036664229 | I4: =1/(1+H4/12) -> 0.99695395
A5: 2 | B5: ='Cash Flows - Scenario 1'!M5 -> 40780094 | C5: =MAX(0,-B5) -> 0 | D5: =I27 -> 0.9349598 | E5: =C5*D5 -> 0 | G5: 2 | H5: ='CIR Scenarios'!B5 -> 0.03432227 | I5: =I4/(1+H5/12) -> 0.99411061
A6: 3 | B6: ='Cash Flows - Scenario 1'!M6 -> 60964970 | C6: =MAX(0,-B6) -> 0 | D6: =I39 -> 0.90489135 | E6: =C6*D6 -> 0 | G6: 3 | H6: ='CIR Scenarios'!B6 -> 0.034482851 | I6: =I5/(1+H6/12) -> 0.99126215
A7: 4 | B7: ='Cash Flows - Scenario 1'!M7 -> 81210061 | C7: =MAX(0,-B7) -> 0 | D7: =I51 -> 0.87293707 | E7: =C7*D7 -> 0 | G7: 4 | H7: ='CIR Scenarios'!B7 -> 0.032157703 | I7: =I6/(1+H7/12) -> 0.98861285
A8: 5 | B8: ='Cash Flows - Scenario 1'!M8 -> 1210287 | C8: =MAX(0,-B8) -> 0 | D8: =I63 -> 0.84391226 | E8: =C8*D8 -> 0 | G8: 5 | H8: ='CIR Scenarios'!B8 -> 0.026269906 | I8: =I7/(1+H8/12) -> 0.98645335
A9: SGPV (Scenario Greatest PV): | E9: =MAX(E4:E8) -> 0 | G9: 6 | H9: ='CIR Scenarios'!B9 -> 0.032562603 | I9: =I8/(1+H9/12) -> 0.9837838
G10: 7 | H10: ='CIR Scenarios'!B10 -> 0.035455093 | I10: =I9/(1+H10/12) -> 0.98088569
G11: 8 | H11: ='CIR Scenarios'!B11 -> 0.036153921 | I11: =I10/(1+H11/12) -> 0.97793933
G12: 9 | H12: ='CIR Scenarios'!B12 -> 0.035422735 | I12: =I11/(1+H12/12) -> 0.97506105
G13: 10 | H13: ='CIR Scenarios'!B13 -> 0.034189958 | I13: =I12/(1+H13/12) -> 0.97229083
G14: 11 | H14: ='CIR Scenarios'!B14 -> 0.032146135 | I14: =I13/(1+H14/12) -> 0.96969318
G15: 12 | H15: ='CIR Scenarios'!B15 -> 0.039260774 | I15: =I14/(1+H15/12) -> 0.96653095
G16: 13 | H16: ='CIR Scenarios'!B16 -> 0.03857793 | I16: =I15/(1+H16/12) -> 0.96343367
G17: 14 | H17: ='CIR Scenarios'!B17 -> 0.037865215 | I17: =I16/(1+H17/12) -> 0.96040318
G18: 15 | H18: ='CIR Scenarios'!B18 -> 0.037874638 | I18: =I17/(1+H18/12) -> 0.95738148
G19: 16 | H19: ='CIR Scenarios'!B19 -> 0.03474007 | I19: =I18/(1+H19/12) -> 0.95461785
G20: 17 | H20: ='CIR Scenarios'!B20 -> 0.035462381 | I20: =I19/(1+H20/12) -> 0.95180508
G21: 18 | H21: ='CIR Scenarios'!B21 -> 0.035508312 | I21: =I20/(1+H21/12) -> 0.94899697
... G63: 60 | H63: ='CIR Scenarios'!B63 -> 0.026636707 | I63: =I62/(1+H63/12) -> 0.84391226

Sheet All Scenarios Summary
A1: All Scenarios Summary — SGPV and Final Accumulated Cash for 50 Scenarios
A2: Each row = one CIR scenario. SGPV = Scenario Greatest Present Value. Sorted by SGPV descending → top 7 scenarios feed C3 charge.
A3: Scenario # | B3: SGPV ($)_real | C3: SGPV ($) | D3: Worst Year | E3: Final Accum Cash ($) | F3: Avg 5Y Rate
A4: 1 | B4: =C4*5 -> 0 | C4: =X67 -> 0 | D4: =W67 -> 1 | E4: =U67 -> 1210287 | F4: =AVERAGE('CIR Scenarios'!B4:'CIR Scenarios'!B63) -> 0.033990398
A5: 2 | B5: =C5*5 -> 7334853.8 | C5: =X74 -> 1466970.8 | D5: =W74 -> 5 | E5: =U74 -> -1643452.2 | F5: =AVERAGE('CIR Scenarios'!C4:'CIR Scenarios'!C63) -> 0.02274284
A6: 3 | B6: =C6*5 -> 0 | C6: =X81 -> 0 | D6: =W81 -> 1 | E6: =U81 -> 351673.92 | F6: =AVERAGE('CIR Scenarios'!D4:'CIR Scenarios'!D63) -> 0.033441653
A7: 4 | B7: =C7*5 -> 0 | C7: =X88 -> 0 | D7: =W88 -> 1 | E7: =U88 -> 6011191.7 | F7: =AVERAGE('CIR Scenarios'!E4:'CIR Scenarios'!E63) -> 0.052284555
A8: 5 | B8: =C8*5 -> 0 | C8: =X95 -> 0 | D8: =W95 -> 1 | E8: =U95 -> 1221272 | F8: =AVERAGE('CIR Scenarios'!F4:'CIR Scenarios'!F63) -> 0.036806611
A9: 6 | B9: =C9*5 -> 576369.37 | C9: =X102 -> 115273.87 | D9: =W102 -> 5 | E9: =U102 -> -134247.8 | F9: =AVERAGE('CIR Scenarios'!G4:'CIR Scenarios'!G63) -> 0.030515593
A10: 7 | B10: =C10*5 -> 4919264 | C10: =X109 -> 983852.81 | D10: =W109 -> 5 | E10: =U109 -> -1131005.2 | F10: =AVERAGE('CIR Scenarios'!H4:'CIR Scenarios'!H63) -> 0.027912798
A11: 8 | B11: =C11*5 -> 0 | C11: =X116 -> 0 | D11: =W116 -> 1 | E11: =U116 -> 1386091.6 | F11: =AVERAGE('CIR Scenarios'!I4:'CIR Scenarios'!I63) -> 0.038688076
A12: 9 | B12: =C12*5 -> 0 | C12: =X123 -> 0 | D12: =W123 -> 1 | E12: =U123 -> 3437535.7 | F12: =AVERAGE('CIR Scenarios'!J4:'CIR Scenarios'!J63) -> 0.040487449
A13: 10 | B13: =C13*5 -> 0 | C13: =X130 -> 0 | D13: =W130 -> 1 | E13: =U130 -> 6376784.2 | F13: =AVERAGE('CIR Scenarios'!K4:'CIR Scenarios'!K63) -> 0.054492572
A14: 11 | B14: =C14*5 -> 7933735.5 | C14: =X137 -> 1586747.1 | D14: =W137 -> 5 | E14: =U137 -> -1800302.8 | F14: =AVERAGE('CIR Scenarios'!L4:'CIR Scenarios'!L63) -> 0.02528397
A15: 12 | B15: =C15*5 -> 0 | C15: =X144 -> 0 | D15: =W144 -> 1 | E15: =U144 -> 721056.24 | F15: =AVERAGE('CIR Scenarios'!M4:'CIR Scenarios'!M63) -> 0.036105842
A16: 13 | B16: =C16*5 -> 0 | C16: =X151 -> 0 | D16: =W151 -> 1 | E16: =U151 -> 3388546.7 | F16: =AVERAGE('CIR Scenarios'!N4:'CIR Scenarios'!N63) -> 0.043197495
A17: 14 | B17: =C17*5 -> 0 | C17: =X158 -> 0 | D17: =W158 -> 1 | E17: =U158 -> 4021240.6 | F17: =AVERAGE('CIR Scenarios'!O4:'CIR Scenarios'!O63) -> 0.043238497
A18: 15 | B18: =C18*5 -> 0 | C18: =X165 -> 0 | D18: =W165 -> 1 | E18: =U165 -> 9276735.7 | F18: =AVERAGE('CIR Scenarios'!P4:'CIR Scenarios'!P63) -> 0.064781
A19: 16 | B19: =C19*5 -> 0 | C19: =X172 -> 0 | D19: =W172 -> 1 | E19: =U172 -> 757891.17 | F19: =AVERAGE('CIR Scenarios'!Q4:'CIR Scenarios'!Q63) -> 0.031965879
A20: 17 | B20: =C20*5 -> 0 | C20: =X179 -> 0 | D20: =W179 -> 1 | E20: =U179 -> 4132998.1 | F20: =AVERAGE('CIR Scenarios'!R4:'CIR Scenarios'!R63) -> 0.042576678
A21: 18 | B21: =C21*5 -> 0 | C21: =X186 -> 0 | D21: =W186 -> 1 | E21: =U186 -> 144780.16 | F21: =AVERAGE('CIR Scenarios'!S4:'CIR Scenarios'!S63) -> 0.032187693
A22: 19 | B22: =C22*5 -> 0 | C22: =X193 -> 0 | D22: =W193 -> 1 | E22: =U193 -> 1703108.1 | F22: =AVERAGE('CIR Scenarios'!T4:'CIR Scenarios'!T63) -> 0.036326302
A23: 20 | B23: =C23*5 -> 0 | C23: =X200 -> 0 | D23: =W200 -> 1 | E23: =U200 -> 3406395.9 | F23: =AVERAGE('CIR Scenarios'!U4:'CIR Scenarios'!U63) -> 0.042588132
A24: 21 | B24: =C24*5 -> 0 | C24: =X207 -> 0 | D24: =W207 -> 1 | E24: =U207 -> 527122.82 | F24: =AVERAGE('CIR Scenarios'!V4:'CIR Scenarios'!V63) -> 0.035792998
A25: 22 | B25: =C25*5 -> 0 | C25: =X214 -> 0 | D25: =W214 -> 1 | E25: =U214 -> 2775948.9 | F25: =AVERAGE('CIR Scenarios'!W4:'CIR Scenarios'!W63) -> 0.041803635
A26: 23 | B26: =C26*5 -> 0 | C26: =X221 -> 0 | D26: =W221 -> 1 | E26: =U221 -> 2432967 | F26: =AVERAGE('CIR Scenarios'!X4:'CIR Scenarios'!X63) -> 0.041015121
A27: 24 | B27: =C27*5 -> 4425651.8 | C27: =X228 -> 885130.35 | D27: =W228 -> 5 | E27: =U228 -> -1003519 | F27: =AVERAGE('CIR Scenarios'!Y4:'CIR Scenarios'!Y63) -> 0.025133721
A28: 25 | B28: =C28*5 -> 0 | C28: =X235 -> 0 | D28: =W235 -> 1 | E28: =U235 -> 1818959.7 | F28: =AVERAGE('CIR Scenarios'!Z4:'CIR Scenarios'!Z63) -> 0.040029809
A29: 26 | B29: =C29*5 -> 0 | C29: =X242 -> 0 | D29: =W242 -> 1 | E29: =U242 -> 8169217.9 | F29: =AVERAGE('CIR Scenarios'!AA4:'CIR Scenarios'!AA63) -> 0.057627063
A30: 27 | B30: =C30*5 -> 0 | C30: =X249 -> 0 | D30: =W249 -> 1 | E30: =U249 -> 4593306.9 | F30: =AVERAGE('CIR Scenarios'!AB4:'CIR Scenarios'!AB63) -> 0.046720931
A31: 28 | B31: =C31*5 -> 0 | C31: =X256 -> 0 | D31: =W256 -> 1 | E31: =U256 -> 7845322.2 | F31: =AVERAGE('CIR Scenarios'!AC4:'CIR Scenarios'!AC63) -> 0.054624398
A32: 29 | B32: =C32*5 -> 0 | C32: =X263 -> 0 | D32: =W263 -> 1 | E32: =U263 -> 1029184 | F32: =AVERAGE('CIR Scenarios'!AD4:'CIR Scenarios'!AD63) -> 0.034513152
A33: 30 | B33: =C33*5 -> 0 | C33: =X270 -> 0 | D33: =W270 -> 1 | E33: =U270 -> 1165713.5 | F33: =AVERAGE('CIR Scenarios'!AE4:'CIR Scenarios'!AE63) -> 0.033666283
A34: 31 | B34: =C34*5 -> 4967839.1 | C34: =X277 -> 993567.82 | D34: =W277 -> 5 | E34: =U277 -> -1130082.6 | F34: =AVERAGE('CIR Scenarios'!AF4:'CIR Scenarios'!AF63) -> 0.025778277
A35: 32 | B35: =C35*5 -> 0 | C35: =X284 -> 0 | D35: =W284 -> 1 | E35: =U284 -> 6580913.3 | F35: =AVERAGE('CIR Scenarios'!AG4:'CIR Scenarios'!AG63) -> 0.052631633
A36: 33 | B36: =C36*5 -> 0 | C36: =X291 -> 0 | D36: =W291 -> 1 | E36: =U291 -> 10375017 | F36: =AVERAGE('CIR Scenarios'!AH4:'CIR Scenarios'!AH63) -> 0.069170528
A37: 34 | B37: =C37*5 -> 0 | C37: =X298 -> 0 | D37: =W298 -> 1 | E37: =U298 -> 5481896.9 | F37: =AVERAGE('CIR Scenarios'!AI4:'CIR Scenarios'!AI63) -> 0.045832928
A38: 35 | B38: =C38*5 -> 0 | C38: =X305 -> 0 | D38: =W305 -> 1 | E38: =U305 -> 3293031.1 | F38: =AVERAGE('CIR Scenarios'!AJ4:'CIR Scenarios'!AJ63) -> 0.042943729
A39: 36 | B39: =C39*5 -> 5596886.7 | C39: =X312 -> 1119377.3 | D39: =W312 -> 5 | E39: =U312 -> -1291488 | F39: =AVERAGE('CIR Scenarios'!AK4:'CIR Scenarios'!AK63) -> 0.028644042
A40: 37 | B40: =C40*5 -> 0 | C40: =X319 -> 0 | D40: =W319 -> 1 | E40: =U319 -> 11640588 | F40: =AVERAGE('CIR Scenarios'!AL4:'CIR Scenarios'!AL63) -> 0.076474184
A41: 38 | B41: =C41*5 -> 0 | C41: =X326 -> 0 | D41: =W326 -> 1 | E41: =U326 -> 3041029.7 | F41: =AVERAGE('CIR Scenarios'!AM4:'CIR Scenarios'!AM63) -> 0.04399752
A42: 39 | B42: =C42*5 -> 0 | C42: =X333 -> 0 | D42: =W333 -> 1 | E42: =U333 -> 1214742.1 | F42: =AVERAGE('CIR Scenarios'!AN4:'CIR Scenarios'!AN63) -> 0.030347096
A43: 40 | B43: =C43*5 -> 0 | C43: =X340 -> 0 | D43: =W340 -> 1 | E43: =U340 -> 2600068 | F43: =AVERAGE('CIR Scenarios'!AO4:'CIR Scenarios'!AO63) -> 0.036072755
A44: 41 | B44: =C44*5 -> 0 | C44: =X347 -> 0 | D44: =W347 -> 1 | E44: =U347 -> 5603446.8 | F44: =AVERAGE('CIR Scenarios'!AP4:'CIR Scenarios'!AP63) -> 0.050818938
A45: 42 | B45: =C45*5 -> 0 | C45: =X354 -> 0 | D45: =W354 -> 1 | E45: =U354 -> 2171570.9 | F45: =AVERAGE('CIR Scenarios'!AQ4:'CIR Scenarios'!AQ63) -> 0.045143172
A46: 43 | B46: =C46*5 -> 0 | C46: =X361 -> 0 | D46: =W361 -> 1 | E46: =U361 -> 5543282.3 | F46: =AVERAGE('CIR Scenarios'!AR4:'CIR Scenarios'!AR63) -> 0.04981088
A47: 44 | B47: =C47*5 -> 0 | C47: =X368 -> 0 | D47: =W368 -> 1 | E47: =U368 -> 623.71944 | F47: =AVERAGE('CIR Scenarios'!AS4:'CIR Scenarios'!AS63) -> 0.032262565
A48: 45 | B48: =C48*5 -> 0 | C48: =X375 -> 0 | D48: =W375 -> 1 | E48: =U375 -> 2550643 | F48: =AVERAGE('CIR Scenarios'!AT4:'CIR Scenarios'!AT63) -> 0.038851962
A49: 46 | B49: =C49*5 -> 3050740.3 | C49: =X382 -> 610148.05 | D49: =W382 -> 5 | E49: =U382 -> -689764.74 | F49: =AVERAGE('CIR Scenarios'!AU4:'CIR Scenarios'!AU63) -> 0.024556843
A50: 47 | B50: =C50*5 -> 4058649.1 | C50: =X389 -> 811729.83 | D50: =W389 -> 5 | E50: =U389 -> -950167.69 | F50: =AVERAGE('CIR Scenarios'!AV4:'CIR Scenarios'!AV63) -> 0.031542193
A51: 48 | B51: =C51*5 -> 0 | C51: =X396 -> 0 | D51: =W396 -> 1 | E51: =U396 -> 4214293.6 | F51: =AVERAGE('CIR Scenarios'!AW4:'CIR Scenarios'!AW63) -> 0.042802492
A52: 49 | B52: =C52*5 -> 0 | C52: =X403 -> 0 | D52: =W403 -> 1 | E52: =U403 -> 7136048.6 | F52: =AVERAGE('CIR Scenarios'!AX4:'CIR Scenarios'!AX63) -> 0.058836816
A53: 50 | B53: =C53*5 -> 0 | C53: =X410 -> 0 | D53: =W410 -> 1 | E53: =U410 -> 1827784.3 | F53: =AVERAGE('CIR Scenarios'!AY4:'CIR Scenarios'!AY63) -> 0.03881162
A56: → For full year-by-year detail, see 'Cash Flows - Scenario 1' and 'PVAD - Scenario 1' tabs
I62: 1 | J62: 100000000 | K62: =J62*Asset_Coupon -> 4000000 | L62: 20000000 | M62: =AVERAGE('CIR Scenarios'!B4:'CIR Scenarios'!B15) -> 0.034090682 | N62: 0 | O62: =K62+L62+N62 -> 24000000 | P62: =FABN_Face*FABN_Rate -> 3500000 | Q62: 0 | R62: =Expenses -> 50000 | S62: =P62+Q62+R62 -> 3550000 | T62: =O62-S62 -> 20450000 | U62: =T62 -> 20450000 | V62: =MAX(0,-U62) -> 0 | W62: {=PRODUCT(1/(1+'CIR Scenarios'!B4:'CIR Scenarios'!B15/12))} -> 0.96653095 | X62: =V62*W62 -> 0
I63: 2 | J63: 80000000 | K63: =J63*Asset_Coupon -> 3200000 | L63: 20000000 | M63: =AVERAGE('CIR Scenarios'!B16:'CIR Scenarios'!B27) -> 0.033256437 | N63: =IF(U62>0,U62*M63,0) -> 680094.14 | O63: =K63+L63+N63 -> 23880094 | P63: =FABN_Face*FABN_Rate -> 3500000 | Q63: 0 | R63: =Expenses -> 50000 | S63: =P63+Q63+R63 -> 3550000 | T63: =O63-S63 -> 20330094 | U63: =U62+T63 -> 40780094 | V63: =MAX(0,-U63) -> 0 | W63: {=W62*PRODUCT(1/(1+'CIR Scenarios'!B16:'CIR Scenarios'!B27/12))} -> 0.9349598 | X63: =V63*W63 -> 0
I64: 3 | J64: 60000000 | K64: =J64*Asset_Coupon -> 2400000 | L64: 20000000 | M64: =AVERAGE('CIR Scenarios'!B28:'CIR Scenarios'!B39) -> 0.03273351 | N64: =IF(U63>0,U63*M64,0) -> 1334875.6 | O64: =K64+L64+N64 -> 23734876 | P64: =FABN_Face*FABN_Rate -> 3500000 | Q64: 0 | R64: =Expenses -> 50000 | S64: =P64+Q64+R64 -> 3550000 | T64: =O64-S64 -> 20184876 | U64: =U63+T64 -> 60964970 | V64: =MAX(0,-U64) -> 0 | W64: {=W63*PRODUCT(1/(1+'CIR Scenarios'!B28:'CIR Scenarios'!B39/12))} -> 0.90489135 | X64: =V64*W64 -> 0
I65: 4 | J65: 40000000 | K65: =J65*Asset_Coupon -> 1600000 | L65: 20000000 | M65: =AVERAGE('CIR Scenarios'!B40:'CIR Scenarios'!B51) -> 0.036005773 | N65: =IF(U64>0,U64*M65,0) -> 2195090.8 | O65: =K65+L65+N65 -> 23795091 | P65: =FABN_Face*FABN_Rate -> 3500000 | Q65: 0 | R65: =Expenses -> 50000 | S65: =P65+Q65+R65 -> 3550000 | T65: =O65-S65 -> 20245091 | U65: =U64+T65 -> 81210061 | V65: =MAX(0,-U65) -> 0 | W65: {=W64*PRODUCT(1/(1+'CIR Scenarios'!B40:'CIR Scenarios'!B51/12))} -> 0.87293707 | X65: =V65*W65 -> 0
I66: 5 | J66: 20000000 | K66: =J66*Asset_Coupon -> 800000 | L66: 20000000 | M66: =AVERAGE('CIR Scenarios'!B52:'CIR Scenarios'!B63) -> 0.033865587 | N66: =IF(U65>0,U65*M66,0) -> 2750226.4 | O66: =K66+L66+N66 -> 23550226 | P66: =FABN_Face*FABN_Rate -> 3500000 | Q66: 100000000 | R66: =Expenses -> 50000 | S66: =P66+Q66+R66 -> 103550000 | T66: =O66-S66 -> -79999774 | U66: =U65+T66 -> 1210287 | V66: =MAX(0,-U66) -> 0 | W66: {=W65*PRODUCT(1/(1+'CIR Scenarios'!B52:'CIR Scenarios'!B63/12))} -> 0.84391226 | X66: =V66*W66 -> 0
U67: =U66 -> 1210287 | V67: =MAX(0,-U67) -> 0 | W67: =MATCH(MAX(X62:X66),X62:X66,0) -> 1 | X67: =MAX(X62:X66) -> 0
I69: 1 | J69: 100000000 | K69: =J69*Asset_Coupon -> 4000000 | L69: 20000000 | M69: =AVERAGE('CIR Scenarios'!C4:'CIR Scenarios'!C15) -> 0.031772634 | N69: 0 | O69: =K69+L69+N69 -> 24000000 | P69: =FABN_Face*FABN_Rate -> 3500000 | Q69: 0 | R69: =Expenses -> 50000 | S69: =P69+Q69+R69 -> 3550000 | T69: =O69-S69 -> 20450000 | U69: =T69 -> 20450000 | V69: =MAX(0,-U69) -> 0 | W69: {=PRODUCT(1/(1+'CIR Scenarios'!C4:'CIR Scenarios'!C15/12))} -> 0.96876857 | X69: =V69*W69 -> 0
I70: 2 | J70: 80000000 | K70: =J70*Asset_Coupon -> 3200000 | L70: 20000000 | M70: =AVERAGE('CIR Scenarios'!C16:'CIR Scenarios'!C27) -> 0.021589572 | N70: =IF(U69>0,U69*M70,0) -> 441506.75 | O70: =K70+L70+N70 -> 23641507 | P70: =FABN_Face*FABN_Rate -> 3500000 | Q70: 0 | R70: =Expenses -> 50000 | S70: =P70+Q70+R70 -> 3550000 | T70: =O70-S70 -> 20091507 | U70: =U69+T70 -> 40541507 | V70: =MAX(0,-U70) -> 0 | W70: {=W69*PRODUCT(1/(1+'CIR Scenarios'!C16:'CIR Scenarios'!C27/12))} -> 0.94809627 | X70: =V70*W70 -> 0
I71: 3 | J71: 60000000 | K71: =J71*Asset_Coupon -> 2400000 | L71: 20000000 | M71: =AVERAGE('CIR Scenarios'!C28:'CIR Scenarios'!C39) -> 0.018530468 | N71: =IF(U70>0,U70*M71,0) -> 751253.09 | O71: =K71+L71+N71 -> 23151253 | P71: =FABN_Face*FABN_Rate -> 3500000 | Q71: 0 | R71: =Expenses -> 50000 | S71: =P71+Q71+R71 -> 3550000 | T71: =O71-S71 -> 19601253 | U71: =U70+T71 -> 60142760 | V71: =MAX(0,-U71) -> 0 | W71: {=W70*PRODUCT(1/(1+'CIR Scenarios'!C28:'CIR Scenarios'!C39/12))} -> 0.93070288 | X71: =V71*W71 -> 0
I72: 4 | J72: 40000000 | K72: =J72*Asset_Coupon -> 1600000 | L72: 20000000 | M72: =AVERAGE('CIR Scenarios'!C40:'CIR Scenarios'!C51) -> 0.0211992 | N72: =IF(U71>0,U71*M72,0) -> 1274978.4 | O72: =K72+L72+N72 -> 22874978 | P72: =FABN_Face*FABN_Rate -> 3500000 | Q72: 0 | R72: =Expenses -> 50000 | S72: =P72+Q72+R72 -> 3550000 | T72: =O72-S72 -> 19324978 | U72: =U71+T72 -> 79467738 | V72: =MAX(0,-U72) -> 0 | W72: {=W71*PRODUCT(1/(1+'CIR Scenarios'!C40:'CIR Scenarios'!C51/12))} -> 0.91119778 | X72: =V72*W72 -> 0
I73: 5 | J73: 20000000 | K73: =J73*Asset_Coupon -> 800000 | L73: 20000000 | M73: =AVERAGE('CIR Scenarios'!C52:'CIR Scenarios'!C63) -> 0.020622326 | N73: =IF(U72>0,U72*M73,0) -> 1638809.6 | O73: =K73+L73+N73 -> 22438810 | P73: =FABN_Face*FABN_Rate -> 3500000 | Q73: 100000000 | R73: =Expenses -> 50000 | S73: =P73+Q73+R73 -> 103550000 | T73: =O73-S73 -> -81111190 | U73: =U72+T73 -> -1643452.2 | V73: =MAX(0,-U73) -> 1643452.2 | W73: {=W72*PRODUCT(1/(1+'CIR Scenarios'!C52:'CIR Scenarios'!C63/12))} -> 0.89261543 | X73: =V73*W73 -> 1466970.8
U74: =U73 -> -1643452.2 | V74: =MAX(0,-U74) -> 1643452.2 | W74: =MATCH(MAX(X69:X73),X69:X73,0) -> 5 | X74: =MAX(X69:X73) -> 1466970.8
I76: 1 | J76: 100000000 | K76: =J76*Asset_Coupon -> 4000000 | L76: 20000000 | M76: =AVERAGE('CIR Scenarios'!D4:'CIR Scenarios'!D15) -> 0.046593811 | N76: 0 | O76: =K76+L76+N76 -> 24000000 | P76: =FABN_Face*FABN_Rate -> 3500000 | Q76: 0 | R76: =Expenses -> 50000 | S76: =P76+Q76+R76 -> 3550000 | T76: =O76-S76 -> 20450000 | U76: =T76 -> 20450000 | V76: =MAX(0,-U76) -> 0 | W76: {=PRODUCT(1/(1+'CIR Scenarios'!D4:'CIR Scenarios'!D15/12))} -> 0.95456148 | X76: =V76*W76 -> 0
I77: 2 | J77: 80000000 | K77: =J77*Asset_Coupon -> 3200000 | L77: 20000000 | M77: =AVERAGE('CIR Scenarios'!D16:'CIR Scenarios'!D27) -> 0.033652753 | N77: =IF(U76>0,U76*M77,0) -> 688198.8 | O77: =K77+L77+N77 -> 23888199 | P77: =FABN_Face*FABN_Rate -> 3500000 | Q77: 0 | R77: =Expenses -> 50000 | S77: =P77+Q77+R77 -> 3550000 | T77: =O77-S77 -> 20338199 | U77: =U76+T77 -> 40788199 | V77: =MAX(0,-U77) -> 0 | W77: {=W76*PRODUCT(1/(1+'CIR Scenarios'!D16:'CIR Scenarios'!D27/12))} -> 0.92301648 | X77: =V77*W77 -> 0
I78: 3 | J78: 60000000 | K78: =J78*Asset_Coupon -> 2400000 | L78: 20000000 | M78: =AVERAGE('CIR Scenarios'!D28:'CIR Scenarios'!D39) -> 0.026379501 | N78: =IF(U77>0,U77*M78,0) -> 1075972.3 | O78: =K78+L78+N78 -> 23475972 | P78: =FABN_Face*FABN_Rate -> 3500000 | Q78: 0 | R78: =Expenses -> 50000 | S78: =P78+Q78+R78 -> 3550000 | T78: =O78-S78 -> 19925972 | U78: =U77+T78 -> 60714171 | V78: =MAX(0,-U78) -> 0 | W78: {=W77*PRODUCT(1/(1+'CIR Scenarios'!D28:'CIR Scenarios'!D39/12))} -> 0.89901257 | X78: =V78*W78 -> 0
I79: 4 | J79: 40000000 | K79: =J79*Asset_Coupon -> 1600000 | L79: 20000000 | M79: =AVERAGE('CIR Scenarios'!D40:'CIR Scenarios'!D51) -> 0.027107877 | N79: =IF(U78>0,U78*M79,0) -> 1645832.3 | O79: =K79+L79+N79 -> 23245832 | P79: =FABN_Face*FABN_Rate -> 3500000 | Q79: 0 | R79: =Expenses -> 50000 | S79: =P79+Q79+R79 -> 3550000 | T79: =O79-S79 -> 19695832 | U79: =U78+T79 -> 80410003 | V79: =MAX(0,-U79) -> 0 | W79: {=W78*PRODUCT(1/(1+'CIR Scenarios'!D40:'CIR Scenarios'!D51/12))} -> 0.87499659 | X79: =V79*W79 -> 0
I80: 5 | J80: 20000000 | K80: =J80*Asset_Coupon -> 800000 | L80: 20000000 | M80: =AVERAGE('CIR Scenarios'!D52:'CIR Scenarios'!D63) -> 0.033474324 | N80: =IF(U79>0,U79*M80,0) -> 2691670.5 | O80: =K80+L80+N80 -> 23491670 | P80: =FABN_Face*FABN_Rate -> 3500000 | Q80: 100000000 | R80: =Expenses -> 50000 | S80: =P80+Q80+R80 -> 103550000 | T80: =O80-S80 -> -80058330 | U80: =U79+T80 -> 351673.92 | V80: =MAX(0,-U80) -> 0 | W80: {=W79*PRODUCT(1/(1+'CIR Scenarios'!D52:'CIR Scenarios'!D63/12))} -> 0.84623175 | X80: =V80*W80 -> 0
U81: =U80 -> 351673.92 | V81: =MAX(0,-U81) -> 0 | W81: =MATCH(MAX(X76:X80),X76:X80,0) -> 1 | X81: =MAX(X76:X80) -> 0
I83: 1 | J83: 100000000 | K83: =J83*Asset_Coupon -> 4000000 | L83: 20000000 | M83: =AVERAGE('CIR Scenarios'!E4:'CIR Scenarios'!E15) -> 0.041252201 | N83: 0 | O83: =K83+L83+N83 -> 24000000 | P83: =FABN_Face*FABN_Rate -> 3500000 | Q83: 0 | R83: =Expenses -> 50000 | S83: =P83+Q83+R83 -> 3550000 | T83: =O83-S83 -> 20450000 | U83: =T83 -> 20450000 | V83: =MAX(0,-U83) -> 0 | W83: {=PRODUCT(1/(1+'CIR Scenarios'!E4:'CIR Scenarios'!E15/12))} -> 0.95965681 | X83: =V83*W83 -> 0
I84: 2 | J84: 80000000 | K84: =J84*Asset_Coupon -> 3200000 | L84: 20000000 | M84: =AVERAGE('CIR Scenarios'!E16:'CIR Scenarios'!E27) -> 0.050865353 | N84: =IF(U83>0,U83*M84,0) -> 1040196.5 | O84: =K84+L84+N84 -> 24240196 | P84: =FABN_Face*FABN_Rate -> 3500000 | Q84: 0 | R84: =Expenses -> 50000 | S84: =P84+Q84+R84 -> 3550000 | T84: =O84-S84 -> 20690196 | U84: =U83+T84 -> 41140196 | V84: =MAX(0,-U84) -> 0 | W84: {=W83*PRODUCT(1/(1+'CIR Scenarios'!E16:'CIR Scenarios'!E27/12))} -> 0.91216234 | X84: =V84*W84 -> 0
I85: 3 | J85: 60000000 | K85: =J85*Asset_Coupon -> 2400000 | L85: 20000000 | M85: =AVERAGE('CIR Scenarios'!E28:'CIR Scenarios'!E39) -> 0.051202762 | N85: =IF(U84>0,U84*M85,0) -> 2106491.7 | O85: =K85+L85+N85 -> 24506492 | P85: =FABN_Face*FABN_Rate -> 3500000 | Q85: 0 | R85: =Expenses -> 50000 | S85: =P85+Q85+R85 -> 3550000 | T85: =O85-S85 -> 20956492 | U85: =U84+T85 -> 62096688 | V85: =MAX(0,-U85) -> 0 | W85: {=W84*PRODUCT(1/(1+'CIR Scenarios'!E28:'CIR Scenarios'!E39/12))} -> 0.86672746 | X85: =V85*W85 -> 0
I86: 4 | J86: 40000000 | K86: =J86*Asset_Coupon -> 1600000 | L86: 20000000 | M86: =AVERAGE('CIR Scenarios'!E40:'CIR Scenarios'!E51) -> 0.059144089 | N86: =IF(U85>0,U85*M86,0) -> 3672652.1 | O86: =K86+L86+N86 -> 25272652 | P86: =FABN_Face*FABN_Rate -> 3500000 | Q86: 0 | R86: =Expenses -> 50000 | S86: =P86+Q86+R86 -> 3550000 | T86: =O86-S86 -> 21722652 | U86: =U85+T86 -> 83819340 | V86: =MAX(0,-U86) -> 0 | W86: {=W85*PRODUCT(1/(1+'CIR Scenarios'!E40:'CIR Scenarios'!E51/12))} -> 0.81707108 | X86: =V86*W86 -> 0
I87: 5 | J87: 20000000 | K87: =J87*Asset_Coupon -> 800000 | L87: 20000000 | M87: =AVERAGE('CIR Scenarios'!E52:'CIR Scenarios'!E63) -> 0.058958368 | N87: =IF(U86>0,U86*M87,0) -> 4941851.5 | O87: =K87+L87+N87 -> 25741852 | P87: =FABN_Face*FABN_Rate -> 3500000 | Q87: 100000000 | R87: =Expenses -> 50000 | S87: =P87+Q87+R87 -> 103550000 | T87: =O87-S87 -> -77808148 | U87: =U86+T87 -> 6011191.7 | V87: =MAX(0,-U87) -> 0 | W87: {=W86*PRODUCT(1/(1+'CIR Scenarios'!E52:'CIR Scenarios'!E63/12))} -> 0.77040237 | X87: =V87*W87 -> 0
U88: =U87 -> 6011191.7 | V88: =MAX(0,-U88) -> 0 | W88: =MATCH(MAX(X83:X87),X83:X87,0) -> 1 | X88: =MAX(X83:X87) -> 0
I90: 1 | J90: 100000000 | K90: =J90*Asset_Coupon -> 4000000 | L90: 20000000 | M90: =AVERAGE('CIR Scenarios'!F4:'CIR Scenarios'!F15) -> 0.043417373 | N90: 0 | O90: =K90+L90+N90 -> 24000000 | P90: =FABN_Face*FABN_Rate -> 3500000 | Q90: 0 | R90: =Expenses -> 50000 | S90: =P90+Q90+R90 -> 3550000 | T90: =O90-S90 -> 20450000 | U90: =T90 -> 20450000 | V90: =MAX(0,-U90) -> 0 | W90: {=PRODUCT(1/(1+'CIR Scenarios'!F4:'CIR Scenarios'!F15/12))} -> 0.95758689 | X90: =V90*W90 -> 0
I91: 2 | J91: 80000000 | K91: =J91*Asset_Coupon -> 3200000 | L91: 20000000 | M91: =AVERAGE('CIR Scenarios'!F16:'CIR Scenarios'!F27) -> 0.038651983 | N91: =IF(U90>0,U90*M91,0) -> 790433.06 | O91: =K91+L91+N91 -> 23990433 | P91: =FABN_Face*FABN_Rate -> 3500000 | Q91: 0 | R91: =Expenses -> 50000 | S91: =P91+Q91+R91 -> 3550000 | T91: =O91-S91 -> 20440433 | U91: =U90+T91 -> 40890433 | V91: =MAX(0,-U91) -> 0 | W91: {=W90*PRODUCT(1/(1+'CIR Scenarios'!F16:'CIR Scenarios'!F27/12))} -> 0.92133846 | X91: =V91*W91 -> 0
I92: 3 | J92: 60000000 | K92: =J92*Asset_Coupon -> 2400000 | L92: 20000000 | M92: =AVERAGE('CIR Scenarios'!F28:'CIR Scenarios'!F39) -> 0.037885123 | N92: =IF(U91>0,U91*M92,0) -> 1549139.1 | O92: =K92+L92+N92 -> 23949139 | P92: =FABN_Face*FABN_Rate -> 3500000 | Q92: 0 | R92: =Expenses -> 50000 | S92: =P92+Q92+R92 -> 3550000 | T92: =O92-S92 -> 20399139 | U92: =U91+T92 -> 61289572 | V92: =MAX(0,-U92) -> 0 | W92: {=W91*PRODUCT(1/(1+'CIR Scenarios'!F28:'CIR Scenarios'!F39/12))} -> 0.88714078 | X92: =V92*W92 -> 0
I93: 4 | J93: 40000000 | K93: =J93*Asset_Coupon -> 1600000 | L93: 20000000 | M93: =AVERAGE('CIR Scenarios'!F40:'CIR Scenarios'!F51) -> 0.028499385 | N93: =IF(U92>0,U92*M93,0) -> 1746715.1 | O93: =K93+L93+N93 -> 23346715 | P93: =FABN_Face*FABN_Rate -> 3500000 | Q93: 0 | R93: =Expenses -> 50000 | S93: =P93+Q93+R93 -> 3550000 | T93: =O93-S93 -> 19796715 | U93: =U92+T93 -> 81086287 | V93: =MAX(0,-U93) -> 0 | W93: {=W92*PRODUCT(1/(1+'CIR Scenarios'!F40:'CIR Scenarios'!F51/12))} -> 0.86224407 | X93: =V93*W93 -> 0
I94: 5 | J94: 20000000 | K94: =J94*Asset_Coupon -> 800000 | L94: 20000000 | M94: =AVERAGE('CIR Scenarios'!F52:'CIR Scenarios'!F63) -> 0.035579194 | N94: =IF(U93>0,U93*M94,0) -> 2884984.7 | O94: =K94+L94+N94 -> 23684985 | P94: =FABN_Face*FABN_Rate -> 3500000 | Q94: 100000000 | R94: =Expenses -> 50000 | S94: =P94+Q94+R94 -> 103550000 | T94: =O94-S94 -> -79865015 | U94: =U93+T94 -> 1221272 | V94: =MAX(0,-U94) -> 0 | W94: {=W93*PRODUCT(1/(1+'CIR Scenarios'!F52:'CIR Scenarios'!F63/12))} -> 0.83215015 | X94: =V94*W94 -> 0
U95: =U94 -> 1221272 | V95: =MAX(0,-U95) -> 0 | W95: =MATCH(MAX(X90:X94),X90:X94,0) -> 1 | X95: =MAX(X90:X94) -> 0
I97: 1 | J97: 100000000 | K97: =J97*Asset_Coupon -> 4000000 | L97: 20000000 | M97: =AVERAGE('CIR Scenarios'!G4:'CIR Scenarios'!G15) -> 0.037227713 | N97: 0 | O97: =K97+L97+N97 -> 24000000 | P97: =FABN_Face*FABN_Rate -> 3500000 | Q97: 0 | R97: =Expenses -> 50000 | S97: =P97+Q97+R97 -> 3550000 | T97: =O97-S97 -> 20450000 | U97: =T97 -> 20450000 | V97: =MAX(0,-U97) -> 0 | W97: {=PRODUCT(1/(1+'CIR Scenarios'!G4:'CIR Scenarios'!G15/12))} -> 0.96351258 | X97: =V97*W97 -> 0
I98: 2 | J98: 80000000 | K98: =J98*Asset_Coupon -> 3200000 | L98: 20000000 | M98: =AVERAGE('CIR Scenarios'!G16:'CIR Scenarios'!G27) -> 0.031678439 | N98: =IF(U97>0,U97*M98,0) -> 647824.08 | O98: =K98+L98+N98 -> 23847824 | P98: =FABN_Face*FABN_Rate -> 3500000 | Q98: 0 | R98: =Expenses -> 50000 | S98: =P98+Q98+R98 -> 3550000 | T98: =O98-S98 -> 20297824 | U98: =U97+T98 -> 40747824 | V98: =MAX(0,-U98) -> 0 | W98: {=W97*PRODUCT(1/(1+'CIR Scenarios'!G16:'CIR Scenarios'!G27/12))} -> 0.93350816 | X98: =V98*W98 -> 0
I99: 3 | J99: 60000000 | K99: =J99*Asset_Coupon -> 2400000 | L99: 20000000 | M99: =AVERAGE('CIR Scenarios'!G28:'CIR Scenarios'!G39) -> 0.032685545 | N99: =IF(U98>0,U98*M99,0) -> 1331864.8 | O99: =K99+L99+N99 -> 23731865 | P99: =FABN_Face*FABN_Rate -> 3500000 | Q99: 0 | R99: =Expenses -> 50000 | S99: =P99+Q99+R99 -> 3550000 | T99: =O99-S99 -> 20181865 | U99: =U98+T99 -> 60929689 | V99: =MAX(0,-U99) -> 0 | W99: {=W98*PRODUCT(1/(1+'CIR Scenarios'!G28:'CIR Scenarios'!G39/12))} -> 0.90353015 | X99: =V99*W99 -> 0
I100: 4 | J100: 40000000 | K100: =J100*Asset_Coupon -> 1600000 | L100: 20000000 | M100: =AVERAGE('CIR Scenarios'!G40:'CIR Scenarios'!G51) -> 0.023836408 | N100: =IF(U99>0,U99*M100,0) -> 1452344.9 | O100: =K100+L100+N100 -> 23052345 | P100: =FABN_Face*FABN_Rate -> 3500000 | Q100: 0 | R100: =Expenses -> 50000 | S100: =P100+Q100+R100 -> 3550000 | T100: =O100-S100 -> 19502345 | U100: =U99+T100 -> 80432034 | V100: =MAX(0,-U100) -> 0 | W100: {=W99*PRODUCT(1/(1+'CIR Scenarios'!G40:'CIR Scenarios'!G51/12))} -> 0.88226888 | X100: =V100*W100 -> 0
I101: 5 | J101: 20000000 | K101: =J101*Asset_Coupon -> 800000 | L101: 20000000 | M101: =AVERAGE('CIR Scenarios'!G52:'CIR Scenarios'!G63) -> 0.027149859 | N101: =IF(U100>0,U100*M101,0) -> 2183718.4 | O101: =K101+L101+N101 -> 22983718 | P101: =FABN_Face*FABN_Rate -> 3500000 | Q101: 100000000 | R101: =Expenses -> 50000 | S101: =P101+Q101+R101 -> 103550000 | T101: =O101-S101 -> -80566282 | U101: =U100+T101 -> -134247.8 | V101: =MAX(0,-U101) -> 134247.8 | W101: {=W100*PRODUCT(1/(1+'CIR Scenarios'!G52:'CIR Scenarios'!G63/12))} -> 0.85866489 | X101: =V101*W101 -> 115273.87
U102: =U101 -> -134247.8 | V102: =MAX(0,-U102) -> 134247.8 | W102: =MATCH(MAX(X97:X101),X97:X101,0) -> 5 | X102: =MAX(X97:X101) -> 115273.87
I104: 1 | J104: 100000000 | K104: =J104*Asset_Coupon -> 4000000 | L104: 20000000 | M104: =AVERAGE('CIR Scenarios'!H4:'CIR Scenarios'!H15) -> 0.039129849 | N104: 0 | O104: =K104+L104+N104 -> 24000000 | P104: =FABN_Face*FABN_Rate -> 3500000 | Q104: 0 | R104: =Expenses -> 50000 | S104: =P104+Q104+R104 -> 3550000 | T104: =O104-S104 -> 20450000 | U104: =T104 -> 20450000 | V104: =MAX(0,-U104) -> 0 | W104: {=PRODUCT(1/(1+'CIR Scenarios'!H4:'CIR Scenarios'!H15/12))} -> 0.96168712 | X104: =V104*W104 -> 0
I105: 2 | J105: 80000000 | K105: =J105*Asset_Coupon -> 3200000 | L105: 20000000 | M105: =AVERAGE('CIR Scenarios'!H16:'CIR Scenarios'!H27) -> 0.036251869 | N105: =IF(U104>0,U104*M105,0) -> 741350.72 | O105: =K105+L105+N105 -> 23941351 | P105: =FABN_Face*FABN_Rate -> 3500000 | Q105: 0 | R105: =Expenses -> 50000 | S105: =P105+Q105+R105 -> 3550000 | T105: =O105-S105 -> 20391351 | U105: =U104+T105 -> 40841351 | V105: =MAX(0,-U105) -> 0 | W105: {=W104*PRODUCT(1/(1+'CIR Scenarios'!H16:'CIR Scenarios'!H27/12))} -> 0.92750003 | X105: =V105*W105 -> 0
I106: 3 | J106: 60000000 | K106: =J106*Asset_Coupon -> 2400000 | L106: 20000000 | M106: =AVERAGE('CIR Scenarios'!H28:'CIR Scenarios'!H39) -> 0.022785169 | N106: =IF(U105>0,U105*M106,0) -> 930577.09 | O106: =K106+L106+N106 -> 23330577 | P106: =FABN_Face*FABN_Rate -> 3500000 | Q106: 0 | R106: =Expenses -> 50000 | S106: =P106+Q106+R106 -> 3550000 | T106: =O106-S106 -> 19780577 | U106: =U105+T106 -> 60621928 | V106: =MAX(0,-U106) -> 0 | W106: {=W105*PRODUCT(1/(1+'CIR Scenarios'!H28:'CIR Scenarios'!H39/12))} -> 0.90662617 | X106: =V106*W106 -> 0
I107: 4 | J107: 40000000 | K107: =J107*Asset_Coupon -> 1600000 | L107: 20000000 | M107: =AVERAGE('CIR Scenarios'!H40:'CIR Scenarios'!H51) -> 0.018583038 | N107: =IF(U106>0,U106*M107,0) -> 1126539.6 | O107: =K107+L107+N107 -> 22726540 | P107: =FABN_Face*FABN_Rate -> 3500000 | Q107: 0 | R107: =Expenses -> 50000 | S107: =P107+Q107+R107 -> 3550000 | T107: =O107-S107 -> 19176540 | U107: =U106+T107 -> 79798467 | V107: =MAX(0,-U107) -> 0 | W107: {=W106*PRODUCT(1/(1+'CIR Scenarios'!H40:'CIR Scenarios'!H51/12))} -> 0.88994684 | X107: =V107*W107 -> 0
I108: 5 | J108: 20000000 | K108: =J108*Asset_Coupon -> 800000 | L108: 20000000 | M108: =AVERAGE('CIR Scenarios'!H52:'CIR Scenarios'!H63) -> 0.022814066 | N108: =IF(U107>0,U107*M108,0) -> 1820527.5 | O108: =K108+L108+N108 -> 22620527 | P108: =FABN_Face*FABN_Rate -> 3500000 | Q108: 100000000 | R108: =Expenses -> 50000 | S108: =P108+Q108+R108 -> 103550000 | T108: =O108-S108 -> -80929473 | U108: =U107+T108 -> -1131005.2 | V108: =MAX(0,-U108) -> 1131005.2 | W108: {=W107*PRODUCT(1/(1+'CIR Scenarios'!H52:'CIR Scenarios'!H63/12))} -> 0.86989241 | X108: =V108*W108 -> 983852.81
U109: =U108 -> -1131005.2 | V109: =MAX(0,-U109) -> 1131005.2 | W109: =MATCH(MAX(X104:X108),X104:X108,0) -> 5 | X109: =MAX(X104:X108) -> 983852.81
I111: 1 | J111: 100000000 | K111: =J111*Asset_Coupon -> 4000000 | L111: 20000000 | M111: =AVERAGE('CIR Scenarios'!I4:'CIR Scenarios'!I15) -> 0.048777672 | N111: 0 | O111: =K111+L111+N111 -> 24000000 | P111: =FABN_Face*FABN_Rate -> 3500000 | Q111: 0 | R111: =Expenses -> 50000 | S111: =P111+Q111+R111 -> 3550000 | T111: =O111-S111 -> 20450000 | U111: =T111 -> 20450000 | V111: =MAX(0,-U111) -> 0 | W111: {=PRODUCT(1/(1+'CIR Scenarios'!I4:'CIR Scenarios'!I15/12))} -> 0.95248782 | X111: =V111*W111 -> 0
I112: 2 | J112: 80000000 | K112: =J112*Asset_Coupon -> 3200000 | L112: 20000000 | M112: =AVERAGE('CIR Scenarios'!I16:'CIR Scenarios'!I27) -> 0.038636384 | N112: =IF(U111>0,U111*M112,0) -> 790114.06 | O112: =K112+L112+N112 -> 23990114 | P112: =FABN_Face*FABN_Rate -> 3500000 | Q112: 0 | R112: =Expenses -> 50000 | S112: =P112+Q112+R112 -> 3550000 | T112: =O112-S112 -> 20440114 | U112: =U111+T112 -> 40890114 | V112: =MAX(0,-U112) -> 0 | W112: {=W111*PRODUCT(1/(1+'CIR Scenarios'!I16:'CIR Scenarios'!I27/12))} -> 0.91644641 | X112: =V112*W112 -> 0
I113: 3 | J113: 60000000 | K113: =J113*Asset_Coupon -> 2400000 | L113: 20000000 | M113: =AVERAGE('CIR Scenarios'!I28:'CIR Scenarios'!I39) -> 0.038169123 | N113: =IF(U112>0,U112*M113,0) -> 1560739.8 | O113: =K113+L113+N113 -> 23960740 | P113: =FABN_Face*FABN_Rate -> 3500000 | Q113: 0 | R113: =Expenses -> 50000 | S113: =P113+Q113+R113 -> 3550000 | T113: =O113-S113 -> 20410740 | U113: =U112+T113 -> 61300854 | V113: =MAX(0,-U113) -> 0 | W113: {=W112*PRODUCT(1/(1+'CIR Scenarios'!I28:'CIR Scenarios'!I39/12))} -> 0.88217929 | X113: =V113*W113 -> 0
I114: 4 | J114: 40000000 | K114: =J114*Asset_Coupon -> 1600000 | L114: 20000000 | M114: =AVERAGE('CIR Scenarios'!I40:'CIR Scenarios'!I51) -> 0.037077441 | N114: =IF(U113>0,U113*M114,0) -> 2272878.8 | O114: =K114+L114+N114 -> 23872879 | P114: =FABN_Face*FABN_Rate -> 3500000 | Q114: 0 | R114: =Expenses -> 50000 | S114: =P114+Q114+R114 -> 3550000 | T114: =O114-S114 -> 20322879 | U114: =U113+T114 -> 81623733 | V114: =MAX(0,-U114) -> 0 | W114: {=W113*PRODUCT(1/(1+'CIR Scenarios'!I40:'CIR Scenarios'!I51/12))} -> 0.85011804 | X114: =V114*W114 -> 0
...

Sheet C3 Calculation
A1: C3 Risk-Based Capital Charge — CTE Weighting of Top 7 Adverse Scenarios
A2: The C3 charge is a Conditional Tail Expectation (CTE) weighted average of the 7 worst-case SGPVs from the 50 stochastic scenarios. CTE(92-98) regulation requires 50 scenarios; weights emphasize the 4th worst (95th percentile) most heavily.
A4: SECTION 1: CTE Weighting — Top 7 Adverse Scenarios
A5: Rank | B5: Scenario # | C5: SGPV ($) | D5: CTE Weight | E5: Weighted SGPV ($) | F5: Percentile (approx)
A6: 1 | B6: =MATCH(LARGE('All Scenarios Summary'!C$4:C$53,A6),'All Scenarios Summary'!C$4:C$53,0) -> 11 | C6: =LARGE('All Scenarios Summary'!C$4:C$53,A6) -> 1586747.1 | D6: 0.1 | E6: =C6*D6 -> 158674.71 | F6: 98th
A7: 2 | B7: =MATCH(LARGE('All Scenarios Summary'!C$4:C$53,A7),'All Scenarios Summary'!C$4:C$53,0) -> 2 | C7: =LARGE('All Scenarios Summary'!C$4:C$53,A7) -> 1466970.8 | D7: 0.1 | E7: =C7*D7 -> 146697.08 | F7: 96th
A8: 3 | B8: =MATCH(LARGE('All Scenarios Summary'!C$4:C$53,A8),'All Scenarios Summary'!C$4:C$53,0) -> 36 | C8: =LARGE('All Scenarios Summary'!C$4:C$53,A8) -> 1119377.3 | D8: 0.1 | E8: =C8*D8 -> 111937.73 | F8: 94th
A9: 4 | B9: =MATCH(LARGE('All Scenarios Summary'!C$4:C$53,A9),'All Scenarios Summary'!C$4:C$53,0) -> 31 | C9: =LARGE('All Scenarios Summary'!C$4:C$53,A9) -> 993567.82 | D9: 0.4 | E9: =C9*D9 -> 397427.13 | F9: 92nd
A10: 5 | B10: =MATCH(LARGE('All Scenarios Summary'!C$4:C$53,A10),'All Scenarios Summary'!C$4:C$53,0) -> 7 | C10: =LARGE('All Scenarios Summary'!C$4:C$53,A10) -> 983852.81 | D10: 0.1 | E10: =C10*D10 -> 98385.281 | F10: 90th
A11: 6 | B11: =MATCH(LARGE('All Scenarios Summary'!C$4:C$53,A11),'All Scenarios Summary'!C$4:C$53,0) -> 24 | C11: =LARGE('All Scenarios Summary'!C$4:C$53,A11) -> 885130.35 | D11: 0.1 | E11: =C11*D11 -> 88513.035 | F11: 88th
A12: 7 | B12: =MATCH(LARGE('All Scenarios Summary'!C$4:C$53,A12),'All Scenarios Summary'!C$4:C$53,0) -> 47 | C12: =LARGE('All Scenarios Summary'!C$4:C$53,A12) -> 811729.83 | D12: 0.1 | E12: =C12*D12 -> 81172.983 | F12: 86th
A13: C3 Charge (Pre-Tax): | E13: =SUM(E6:E12) -> 1082807.9
A15: SECTION 2: After-Tax C3 Charge
A16: Tax Rate: | B16: =Tax_Rate -> 0.21
A17: C3 Pre-Tax: | B17: =E13 -> 1082807.9
A18: C3 Post-Tax (= Pre-Tax × (1 − Tax Rate)): | B18: =B17*(1-B16) -> 855418.28
A20: SECTION 3: Shortcut Method Comparison
A21: Shortcut Rate (0.75% of FABN face): | B21: 0.0075
A22: Shortcut C3 ($): | B22: =FABN_Face*B21 -> 750000
A23: Full Calc C3 Post-Tax ($): | B23: =B18 -> 855418.28
A24: Difference (Full - Shortcut): | B24: =B23-B22 -> 105418.28
A26: INTERPRETATION:
A27: The CTE weighting uses the 7 worst scenarios out of 50 (86th–98th percentile). The 4th worst (92nd–95th percentile) receives 40% weight because regulators focus on 'bad but not catastrophic' outcomes. If C3 Post-Tax is close to $750,000 (the 0.75% shortcut), the shortcut is a reasonable approximation. A significant positive difference means the full model reveals greater risk than the shortcut captures.
A31: → To see all 50 scenario results, go to 'All Scenarios Summary' tab

Sheet Sensitivity Analysis
A1: C3 Sensitivity Analysis — How C3 Post-Tax Changes as Key Inputs Vary
A2: Each table shows C3 Post-Tax computed from the frozen 50 CIR scenarios while varying one assumption from the Assumptions sheet. The base case ($750K shortcut) is shown as a reference line. NOTE: These are manual snapshots — Excel Data Table (=TABLE()) cannot be written programmatically.
A4: Table 1: Vary FABN Crediting Rate (FABN_Rate in Assumptions!B3)
A5: ← Lower crediting rate → smaller interest outflow → lower C3
A6: FABN Crediting Rate | B6: Net Interest Spread (Asset Coupon − FABN Rate) | C6: Directional C3 Impact
A7: 0.025 | B7: 0.015 | C7: Lower C3
A8: 0.03 | B8: 0.01 | C8: Lower C3
A9: 0.035 | B9: 0.005 | C9: ◄ BASE CASE
A10: 0.04 | B10: 0 | C10: Higher C3
A11: 0.045 | B11: -0.005 | C11: Higher C3
A12: 0.05 | B12: -0.01 | C12: Higher C3
A14: Table 2: Vary Asset Coupon Rate (Asset_Coupon in Assumptions!B5)
A15: ← Higher coupon → more cash inflow → smaller deficiency → lower C3
A16: Asset Coupon Rate | B16: Annual Coupon Income (Year 1, $100M par) | C16: Directional C3 Impact
A17: 0.03 | B17: 3000000 | C17: Higher C3
A18: 0.035 | B18: 3500000 | C18: Higher C3
A19: 0.04 | B19: 4000000 | C19: ◄ BASE CASE
A20: 0.045 | B20: 4500000 | C20: Lower C3
A21: 0.05 | B21: 5000000 | C21: Lower C3
A22: 0.055 | B22: 5500000 | C22: Lower C3
A24: Table 3: Vary FABN Maturity (FABN_Maturity in Assumptions!B4)
A25: ← Longer maturity → principal repayment delayed → more reinvestment income accumulates → can lower C3, but also extends rate risk
A26: FABN Maturity (years) | B26: FABN Principal Payment Year | C26: Directional C3 Impact (qualitative)
A27: 3 | B27: Year 3 | C27: Higher C3 (less time to accumulate)
A28: 5 | B28: Year 5 | C28: ◄ BASE CASE
A29: 7 | B29: Year 7 | C29: Lower if rates rise; higher if rates fall
A30: 10 | B30: Year 10 | C30: Most sensitive to rate path
A32: Table 4: Vary CIR Volatility σ (CIR_sigma in Assumptions!B12)
A33: ← Higher σ → wider spread of rate scenarios → more extreme low-rate scenarios → higher PVAD in worst cases → higher C3
A34: CIR Volatility (σ) | B34: Rate Std Dev (approx monthly, annualized) | C34: Directional C3 Impact
A35: 0.02 | B35: 0.013856406 | C35: Lower C3
A36: 0.04 | B36: 0.027712813 | C36: Lower C3
A37: 0.06 | B37: 0.041569219 | C37: ◄ BASE CASE
A38: 0.08 | B38: 0.055425626 | C38: Higher C3
A39: 0.1 | B39: 0.069282032 | C39: Higher C3
A41: CURRENT MODEL OUTPUT (live, from Assumptions):
A42: C3 Post-Tax ($): | B42: ='C3 Calculation'!B18 -> 855418.28
A43: Shortcut C3 ($): | B43: ='C3 Calculation'!B22 -> 750000
A44: Difference (Full − Shortcut): | B44: ='C3 Calculation'!B24 -> 105418.28
